Workbook

Sheet ITEM 01
A1: ITENS | B1: DESCRIÇÃO | C1: UND | D1: QUANT | E1: PREÇO UNIT | F1: PREÇO
A2: 1.0 | B2: MOBILIZAÇÃO
A3: 1.1 | B3: Mobilização de equipamentos e pessoas para realização do levantamento | C3: VERBA | D3: 1 | E3: 650 | F3: =D3*E3 -> 650
A4: 2.0 | B4: LEVANTAMENTO TOPOGRÁFICO E INSUMOS DE CAMPO
A5: 2.1 | B5: Levantamento Territorial Cadastral do Limites Georreferenciado por receptores geodésicos de posicionamento por satélite (GNSS) de Dupla frequecia pelo método relativo estático rápido ou stop-go/NTRIP /RTK para pontos de apoio ou para levantar os limites legais (naturais e artificiais do imóvel) para atendimento Manual Técnico para Georreferenciamento de Imóveis Rurais -MTGIR - 2ª Edição. | C5: hectares | D5: 90.5 | E5: 35 | F5: =D5*E5 -> 3167.5
A6: 2.2 | B6: Implantação de Marcos Padrão INCRA com codificação dos vertices e do credenciado | C6: Und | D6: 2 | E6: 150 | F6: =D6*E6 -> 300
A7: 3.0 | B7: ESCRITÓRIO
A8: 3.1 | B8: Elaboração de plantas e peças técnicas em CAD e calculos e memoriais descritivos necessários com impressão em formato ABNT em 3 vias com a elaboração do memorial descritivo, com Anotação de Responsabilidade Técnica - ART | C8: VERBA | D8: 1 | E8: 700 | F8: =D8*E8 -> 700
A9: 3.2 | B9: Elaboração de Planilha ODS para inserção no SIGEF com a Devida Responsabilidade Técnica conforme MTGIR 2° Edição e Lançamento no SIGEF | C9: VERBA | D9: 1 | E9: 500 | F9: =D9*E9 -> 500
A10: 3.3 | B10: Elaboração e Registro do Imóvel no Cadastro Ambiental Rural - CAR no SICAR | C10: VERBA | D10: 1 | E10: 400 | F10: =D10*E10 -> 400
A11: 4.0 | B11: SERVIÇOS DE DESPACHANTE IMOBILIÁRIO
A12: 4.1 | B12: Criação e Registro do Sistma Nacional de Cadastro de Imóvel Rural SNCR para Emissão anual de CCIR ( Area Geral, Remanescente e Desmebrada) | C12: VERBA | D12: 1 | E12: 600 | F12: 500
A13: 4.2 | B13: Criação e Registro do Cadastro de Imóvel do Brasil - CIB na Receita Federal do Brasil | C13: VERBA | D13: 1 | E13: 500 | F13: =D13*E13 -> 500
A14: 4.3 | B14: Regularição o Imposto Territorial Rural - ITR e necessidade de Despachante | C14: VERBA | D14: 1 | E14: 500 | F14: =D14*E14 -> 500
B16: TOTAL | F16: =SUM(F2:F15) -> 7217.5
B20: DESPESAS:
B21: Marcos | C21: 150
B22: Ajudante | C22: 160
B23: Alimentação | C23: 90
B24: combustivel | C24: 100
C25: =SUM(C21:C24) -> 500

Sheet ITEM 02
A1: ITENS | B1: DESCRIÇÃO | C1: UND | D1: QUANT | E1: PREÇO UNIT | F1: PREÇO
A2: 1.0 | B2: MOBILIZAÇÃO
A3: 1.1 | B3: Mobilização de equipamentos e pessoas para realização do levantamento | C3: VERBA | D3: 1 | E3: 650 | F3: =D3*E3 -> 650
A4: 2.0 | B4: LEVANTAMENTO TOPOGRÁFICO E INSUMOS DE CAMPO
A5: 2.1 | B5: Levantamento Territorial Cadastral do Limites Georreferenciado por receptores geodésicos de posicionamento por satélite (GNSS) de Dupla frequecia pelo método relativo estático rápido ou stop-go/NTRIP /RTK para pontos de apoio ou para levantar os limites legais (naturais e artificiais do imóvel) para atendimento Manual Técnico para Georreferenciamento de Imóveis Rurais -MTGIR - 2ª Edição. | C5: hectares | D5: 9 | E5: 25 | F5: =D5*E5 -> 225
A6: 2.2 | B6: Implantação de Marcos Padrão INCRA com codificação dos vertices e do credenciado | C6: Und | D6: 2 | E6: 150 | F6: =D6*E6 -> 300
A7: 3.0 | B7: ESCRITÓRIO
A8: 3.1 | B8: Elaboração de plantas e peças técnicas em CAD e calculos e memoriais descritivos necessários com impressão em formato ABNT em 3 vias com a elaboração do memorial descritivo, com Anotação de Responsabilidade Técnica - ART | C8: VERBA | D8: 1 | E8: 700 | F8: =D8*E8 -> 700
A9: 3.2 | B9: Elaboração de Planilha ODS para inserção no SIGEF com a Devida Responsabilidade Técnica conforme MTGIR 2° Edição e Lançamento no SIGEF | C9: VERBA | D9: 1 | E9: 500 | F9: =D9*E9 -> 500
A10: 3.3 | B10: Elaboração e Registro do Imóvel no Cadastro Ambiental Rural - CAR no SICAR | C10: VERBA | D10: 1 | E10: 400 | F10: =D10*E10 -> 400
A11: 4.0 | B11: SERVIÇOS DE DESPACHANTE IMOBILIÁRIO
A12: 4.1 | B12: Criação e Registro do Sistma Nacional de Cadastro de Imóvel Rural SNCR para Emissão anual de CCIR ( Area Geral, Remanescente e Desmebrada) | C12: VERBA | D12: 1 | E12: 600 | F12: 500
A13: 4.2 | B13: Criação e Registro do Cadastro de Imóvel do Brasil - CIB na Receita Federal do Brasil | C13: VERBA | D13: 1 | E13: 500 | F13: =D13*E13 -> 500
A14: 4.3 | B14: Regularição o Imposto Territorial Rural - ITR e necessidade de Despachante | C14: VERBA | D14: 1 | E14: 500 | F14: =D14*E14 -> 500
B16: TOTAL | F16: =SUM(F2:F15) -> 4275
B20: DESPESAS:
B21: Marcos | C21: 150
B22: Ajudante | C22: 160
B23: Alimentação | C23: 90
B24: combustivel | C24: 100
C25: =SUM(C21:C24) -> 500

Sheet ITEM 03
A1: ITENS | B1: DESCRIÇÃO | C1: UND | D1: QUANT | E1: PREÇO UNIT | F1: PREÇO
A2: 1.0 | B2: MOBILIZAÇÃO
A3: 1.1 | B3: Mobilização de equipamentos e pessoas para realização do levantamento | C3: VERBA | D3: 1 | E3: 650 | F3: =D3*E3 -> 650
A4: 2.0 | B4: LEVANTAMENTO TOPOGRÁFICO E INSUMOS DE CAMPO
A5: 2.1 | B5: Levantamento Territorial Cadastral do Limites Georreferenciado por receptores geodésicos de posicionamento por satélite (GNSS) de Dupla frequecia pelo método relativo estático rápido ou stop-go/NTRIP /RTK para pontos de apoio ou para levantar os limites legais (naturais e artificiais do imóvel) para atendimento Manual Técnico para Georreferenciamento de Imóveis Rurais -MTGIR - 2ª Edição. | C5: hectares | D5: 40.3 | E5: 25 | F5: =D5*E5 -> 1007.5
A6: 2.2 | B6: Implantação de Marcos Padrão INCRA com codificação dos vertices e do credenciado | C6: Und | D6: 2 | E6: 150 | F6: =D6*E6 -> 300
A7: 3.0 | B7: ESCRITÓRIO
A8: 3.1 | B8: Elaboração de plantas e peças técnicas em CAD e calculos e memoriais descritivos necessários com impressão em formato ABNT em 3 vias com a elaboração do memorial descritivo, com Anotação de Responsabilidade Técnica - ART | C8: VERBA | D8: 1 | E8: 700 | F8: =D8*E8 -> 700
A9: 3.2 | B9: Elaboração de Planilha ODS para inserção no SIGEF com a Devida Responsabilidade Técnica conforme MTGIR 2° Edição e Lançamento no SIGEF | C9: VERBA | D9: 1 | E9: 500 | F9: =D9*E9 -> 500
A10: 3.3 | B10: Elaboração e Registro do Imóvel no Cadastro Ambiental Rural - CAR no SICAR | C10: VERBA | D10: 1 | E10: 400 | F10: =D10*E10 -> 400
A11: 4.0 | B11: SERVIÇOS DE DESPACHANTE IMOBILIÁRIO
A12: 4.1 | B12: Criação e Registro do Sistma Nacional de Cadastro de Imóvel Rural SNCR para Emissão anual de CCIR ( Area Geral, Remanescente e Desmebrada) | C12: VERBA | D12: 1 | E12: 600 | F12: 500
A13: 4.2 | B13: Criação e Registro do Cadastro de Imóvel do Brasil - CIB na Receita Federal do Brasil | C13: VERBA | D13: 1 | E13: 500 | F13: =D13*E13 -> 500
A14: 4.3 | B14: Regularição o Imposto Territorial Rural - ITR e necessidade de Despachante | C14: VERBA | D14: 1 | E14: 500 | F14: =D14*E14 -> 500
B16: TOTAL | F16: =SUM(F2:F15) -> 5057.5
B20: DESPESAS:
B21: Marcos | C21: 150
B22: Ajudante | C22: 160
B23: Alimentação | C23: 90
B24: combustivel | C24: 100
C25: 700

Sheet ITEM 04
A1: ITENS | B1: DESCRIÇÃO | C1: UND | D1: QUANT | E1: PREÇO UNIT | F1: PREÇO
A2: 1.0 | B2: MOBILIZAÇÃO
A3: 1.1 | B3: Mobilização de equipamentos e pessoas para realização do levantamento | C3: VERBA | D3: 1 | E3: 650 | F3: =D3*E3 -> 650
A4: 2.0 | B4: LEVANTAMENTO TOPOGRÁFICO E INSUMOS DE CAMPO
A5: 2.1 | B5: Levantamento Territorial Cadastral do Limites Georreferenciado por receptores geodésicos de posicionamento por satélite (GNSS) de Dupla frequecia pelo método relativo estático rápido ou stop-go/NTRIP /RTK para pontos de apoio ou para levantar os limites legais (naturais e artificiais do imóvel) para atendimento Manual Técnico para Georreferenciamento de Imóveis Rurais -MTGIR - 2ª Edição. | C5: hectares | D5: 40.3 | E5: 25 | F5: =D5*E5 -> 1007.5
A6: 2.2 | B6: Implantação de Marcos Padrão INCRA com codificação dos vertices e do credenciado | C6: Und | D6: 2 | E6: 150 | F6: =D6*E6 -> 300
A7: 3.0 | B7: ESCRITÓRIO
A8: 3.1 | B8: Elaboração de plantas e peças técnicas em CAD e calculos e memoriais descritivos necessários com impressão em formato ABNT em 3 vias com a elaboração do memorial descritivo, com Anotação de Responsabilidade Técnica - ART | C8: VERBA | D8: 1 | E8: 700 | F8: =D8*E8 -> 700
A9: 3.2 | B9: Elaboração de Planilha ODS para inserção no SIGEF com a Devida Responsabilidade Técnica conforme MTGIR 2° Edição e Lançamento no SIGEF | C9: VERBA | D9: 1 | E9: 500 | F9: =D9*E9 -> 500
A10: 3.3 | B10: Elaboração e Registro do Imóvel no Cadastro Ambiental Rural - CAR no SICAR | C10: VERBA | D10: 1 | E10: 400 | F10: =D10*E10 -> 400
A11: 4.0 | B11: SERVIÇOS DE DESPACHANTE IMOBILIÁRIO
A12: 4.1 | B12: Criação e Registro do Sistma Nacional de Cadastro de Imóvel Rural SNCR para Emissão anual de CCIR ( Area Geral, Remanescente e Desmebrada) | C12: VERBA | D12: 1 | E12: 600 | F12: 500
A13: 4.2 | B13: Criação e Registro do Cadastro de Imóvel do Brasil - CIB na Receita Federal do Brasil | C13: VERBA | D13: 1 | E13: 500 | F13: =D13*E13 -> 500
A14: 4.3 | B14: Regularição o Imposto Territorial Rural - ITR e necessidade de Despachante | C14: VERBA | D14: 1 | E14: 500 | F14: =D14*E14 -> 500
B16: TOTAL | F16: =SUM(F2:F15) -> 5057.5
B20: DESPESAS:
B21: Marcos | C21: 150
B22: Ajudante | C22: 160
B23: Alimentação | C23: 90
B24: combustivel | C24: 100
C25: 700

Sheet ITEM 05
A1: ITENS | B1: DESCRIÇÃO | C1: UND | D1: QUANT | E1: PREÇO UNIT | F1: PREÇO
A2: 1.0 | B2: MOBILIZAÇÃO
A3: 1.1 | B3: Mobilização de equipamentos e pessoas para realização do levantamento | C3: VERBA | D3: 1 | E3: 650 | F3: =D3*E3 -> 650
A4: 2.0 | B4: LEVANTAMENTO TOPOGRÁFICO E INSUMOS DE CAMPO
A5: 2.1 | B5: Levantamento Territorial Cadastral do Limites Georreferenciado por receptores geodésicos de posicionamento por satélite (GNSS) de Dupla frequecia pelo método relativo estático rápido ou stop-go/NTRIP /RTK para pontos de apoio ou para levantar os limites legais (naturais e artificiais do imóvel) para atendimento Manual Técnico para Georreferenciamento de Imóveis Rurais -MTGIR - 2ª Edição. | C5: hectares | D5: 9 | E5: 25 | F5: =D5*E5 -> 225
A6: 2.2 | B6: Implantação de Marcos Padrão INCRA com codificação dos vertices e do credenciado | C6: Und | D6: 2 | E6: 150 | F6: =D6*E6 -> 300
A7: 3.0 | B7: ESCRITÓRIO
A8: 3.1 | B8: Elaboração de plantas e peças técnicas em CAD e calculos e memoriais descritivos necessários com impressão em formato ABNT em 3 vias com a elaboração do memorial descritivo, com Anotação de Responsabilidade Técnica - ART | C8: VERBA | D8: 1 | E8: 700 | F8: =D8*E8 -> 700
A9: 3.2 | B9: Elaboração de Planilha ODS para inserção no SIGEF com a Devida Responsabilidade Técnica conforme MTGIR 2° Edição e Lançamento no SIGEF | C9: VERBA | D9: 1 | E9: 500 | F9: =D9*E9 -> 500
A10: 3.3 | B10: Elaboração e Registro do Imóvel no Cadastro Ambiental Rural - CAR no SICAR | C10: VERBA | D10: 1 | E10: 400 | F10: =D10*E10 -> 400
A11: 4.0 | B11: SERVIÇOS DE DESPACHANTE IMOBILIÁRIO
A12: 4.1 | B12: Criação e Registro do Sistma Nacional de Cadastro de Imóvel Rural SNCR para Emissão anual de CCIR ( Area Geral, Remanescente e Desmebrada) | C12: VERBA | D12: 1 | E12: 600 | F12: 500
A13: 4.2 | B13: Criação e Registro do Cadastro de Imóvel do Brasil - CIB na Receita Federal do Brasil | C13: VERBA | D13: 1 | E13: 500 | F13: =D13*E13 -> 500
A14: 4.3 | B14: Regularição o Imposto Territorial Rural - ITR e necessidade de Despachante | C14: VERBA | D14: 1 | E14: 500 | F14: =D14*E14 -> 500
B16: TOTAL | F16: =SUM(F2:F15) -> 4275
B20: DESPESAS:
B21: Marcos | C21: 150
B22: Ajudante | C22: 160
B23: Alimentação | C23: 90
B24: combustivel | C24: 100
C25: 700

Sheet ITEM 06
A1: ITENS | B1: DESCRIÇÃO | C1: UND | D1: QUANT | E1: PREÇO UNIT | F1: PREÇO
A2: 1.0 | B2: MOBILIZAÇÃO
A3: 1.1 | B3: Mobilização de equipamentos e pessoas para realização do levantamento | C3: VERBA | D3: 1 | E3: 650 | F3: =D3*E3 -> 650
A4: 2.0 | B4: LEVANTAMENTO TOPOGRÁFICO E INSUMOS DE CAMPO
A5: 2.1 | B5: Levantamento Territorial Cadastral do Limites Georreferenciado por receptores geodésicos de posicionamento por satélite (GNSS) de Dupla frequecia pelo método relativo estático rápido ou stop-go/NTRIP /RTK para pontos de apoio ou para levantar os limites legais (naturais e artificiais do imóvel) para atendimento Manual Técnico para Georreferenciamento de Imóveis Rurais -MTGIR - 2ª Edição. | C5: hectares | D5: 7 | E5: 25 | F5: =D5*E5 -> 175
A6: 2.2 | B6: Implantação de Marcos Padrão INCRA com codificação dos vertices e do credenciado | C6: Und | D6: 2 | E6: 150 | F6: =D6*E6 -> 300
A7: 3.0 | B7: ESCRITÓRIO
A8: 3.1 | B8: Elaboração de plantas e peças técnicas em CAD e calculos e memoriais descritivos necessários com impressão em formato ABNT em 3 vias com a elaboração do memorial descritivo, com Anotação de Responsabilidade Técnica - ART | C8: VERBA | D8: 1 | E8: 700 | F8: =D8*E8 -> 700
A9: 3.2 | B9: Elaboração de Planilha ODS para inserção no SIGEF com a Devida Responsabilidade Técnica conforme MTGIR 2° Edição e Lançamento no SIGEF | C9: VERBA | D9: 1 | E9: 500 | F9: =D9*E9 -> 500
A10: 3.3 | B10: Elaboração e Registro do Imóvel no Cadastro Ambiental Rural - CAR no SICAR | C10: VERBA | D10: 1 | E10: 400 | F10: =D10*E10 -> 400
A11: 4.0 | B11: SERVIÇOS DE DESPACHANTE IMOBILIÁRIO
A12: 4.1 | B12: Criação e Registro do Sistma Nacional de Cadastro de Imóvel Rural SNCR para Emissão anual de CCIR ( Area Geral, Remanescente e Desmebrada) | C12: VERBA | D12: 1 | E12: 600 | F12: 500
A13: 4.2 | B13: Criação e Registro do Cadastro de Imóvel do Brasil - CIB na Receita Federal do Brasil | C13: VERBA | D13: 1 | E13: 500 | F13: =D13*E13 -> 500
A14: 4.3 | B14: Regularição o Imposto Territorial Rural - ITR e necessidade de Despachante | C14: VERBA | D14: 1 | E14: 500 | F14: =D14*E14 -> 500
B16: TOTAL | F16: =SUM(F2:F15) -> 4225
B20: DESPESAS:
B21: Marcos | C21: 150
B22: Ajudante | C22: 160
B23: Alimentação | C23: 90
B24: combustivel | C24: 100
C25: 500

Sheet ITEM07
A1: ITENS | B1: DESCRIÇÃO | C1: UND | D1: QUANT | E1: PREÇO UNIT | F1: PREÇO
A2: 1.0 | B2: MOBILIZAÇÃO
A3: 1.1 | B3: Mobilização de equipamentos e pessoas para realização do levantamento | C3: VERBA | D3: 1 | E3: 650 | F3: =D3*E3 -> 650
A4: 2.0 | B4: LEVANTAMENTO TOPOGRÁFICO E INSUMOS DE CAMPO
A5: 2.1 | B5: Levantamento Territorial Cadastral do Limites Georreferenciado por receptores geodésicos de posicionamento por satélite (GNSS) de Dupla frequecia pelo método relativo estático rápido ou stop-go/NTRIP /RTK para pontos de apoio ou para levantar os limites legais (naturais e artificiais do imóvel) para atendimento Manual Técnico para Georreferenciamento de Imóveis Rurais -MTGIR - 2ª Edição. | C5: hectares | D5: 1.8 | E5: 25 | F5: =D5*E5 -> 45
A6: 2.2 | B6: Implantação de Marcos Padrão INCRA com codificação dos vertices e do credenciado | C6: Und | D6: 2 | E6: 150 | F6: =D6*E6 -> 300
A7: 3.0 | B7: ESCRITÓRIO
A8: 3.1 | B8: Elaboração de plantas e peças técnicas em CAD e calculos e memoriais descritivos necessários com impressão em formato ABNT em 3 vias com a elaboração do memorial descritivo, com Anotação de Responsabilidade Técnica - ART | C8: VERBA | D8: 1 | E8: 700 | F8: =D8*E8 -> 700
A9: 3.2 | B9: Elaboração de Planilha ODS para inserção no SIGEF com a Devida Responsabilidade Técnica conforme MTGIR 2° Edição e Lançamento no SIGEF | C9: VERBA | D9: 1 | E9: 500 | F9: =D9*E9 -> 500
A10: 3.3 | B10: Elaboração e Registro do Imóvel no Cadastro Ambiental Rural - CAR no SICAR | C10: VERBA | D10: 1 | E10: 400 | F10: =D10*E10 -> 400
A11: 4.0 | B11: SERVIÇOS DE DESPACHANTE IMOBILIÁRIO
A12: 4.1 | B12: Criação e Registro do Sistma Nacional de Cadastro de Imóvel Rural SNCR para Emissão anual de CCIR ( Area Geral, Remanescente e Desmebrada) | C12: VERBA | D12: 1 | E12: 600 | F12: 500
A13: 4.2 | B13: Criação e Registro do Cadastro de Imóvel do Brasil - CIB na Receita Federal do Brasil | C13: VERBA | D13: 1 | E13: 500 | F13: =D13*E13 -> 500
A14: 4.3 | B14: Regularição o Imposto Territorial Rural - ITR e necessidade de Despachante | C14: VERBA | D14: 1 | E14: 500 | F14: =D14*E14 -> 500
B16: TOTAL | F16: =SUM(F2:F15) -> 4095
B20: DESPESAS:
B21: Marcos | C21: 150
B22: Ajudante | C22: 160
B23: Alimentação | C23: 90
B24: combustivel | C24: 100
C25: 500

Sheet ITEM 08
A1: ITENS | B1: DESCRIÇÃO | C1: UND | D1: QUANT | E1: PREÇO UNIT | F1: PREÇO
A2: 1.0 | B2: MOBILIZAÇÃO
A3: 1.1 | B3: Mobilização de equipamentos e pessoas para realização do levantamento | C3: VERBA | D3: 1 | E3: 650 | F3: =D3*E3 -> 650
A4: 2.0 | B4: LEVANTAMENTO TOPOGRÁFICO E INSUMOS DE CAMPO
A5: 2.1 | B5: Levantamento Territorial Cadastral do Limites Georreferenciado por receptores geodésicos de posicionamento por satélite (GNSS) de Dupla frequecia pelo método relativo estático rápido ou stop-go/NTRIP /RTK para pontos de apoio ou para levantar os limites legais (naturais e artificiais do imóvel) para atendimento Manual Técnico para Georreferenciamento de Imóveis Rurais -MTGIR - 2ª Edição. | C5: hectares | D5: 3.6 | E5: 25 | F5: =D5*E5 -> 90
A6: 2.2 | B6: Implantação de Marcos Padrão INCRA com codificação dos vertices e do credenciado | C6: Und | D6: 2 | E6: 150 | F6: =D6*E6 -> 300
A7: 3.0 | B7: ESCRITÓRIO
A8: 3.1 | B8: Elaboração de plantas e peças técnicas em CAD e calculos e memoriais descritivos necessários com impressão em formato ABNT em 3 vias com a elaboração do memorial descritivo, com Anotação de Responsabilidade Técnica - ART | C8: VERBA | D8: 1 | E8: 700 | F8: =D8*E8 -> 700
A9: 3.2 | B9: Elaboração de Planilha ODS para inserção no SIGEF com a Devida Responsabilidade Técnica conforme MTGIR 2° Edição e Lançamento no SIGEF | C9: VERBA | D9: 1 | E9: 500 | F9: =D9*E9 -> 500
A10: 3.3 | B10: Elaboração e Registro do Imóvel no Cadastro Ambiental Rural - CAR no SICAR | C10: VERBA | D10: 1 | E10: 400 | F10: =D10*E10 -> 400
A11: 4.0 | B11: SERVIÇOS DE DESPACHANTE IMOBILIÁRIO
A12: 4.1 | B12: Criação e Registro do Sistma Nacional de Cadastro de Imóvel Rural SNCR para Emissão anual de CCIR ( Area Geral, Remanescente e Desmebrada) | C12: VERBA | D12: 1 | E12: 600 | F12: 500
A13: 4.2 | B13: Criação e Registro do Cadastro de Imóvel do Brasil - CIB na Receita Federal do Brasil | C13: VERBA | D13: 1 | E13: 500 | F13: =D13*E13 -> 500
A14: 4.3 | B14: Regularição o Imposto Territorial Rural - ITR e necessidade de Despachante | C14: VERBA | D14: 1 | E14: 500 | F14: =D14*E14 -> 500
B16: TOTAL | F16: =SUM(F2:F15) -> 4140
B20: DESPESAS:
B21: Marcos | C21: 150
B22: Ajudante | C22: 160
B23: Alimentação | C23: 90
B24: combustivel | C24: 100
C25: 500

Sheet ITEM 09
A1: ITENS | B1: DESCRIÇÃO | C1: UND | D1: QUANT | E1: PREÇO UNIT | F1: PREÇO
A2: 1.0 | B2: MOBILIZAÇÃO
A3: 1.1 | B3: Mobilização de equipamentos e pessoas para realização do levantamento | C3: VERBA | D3: 1 | E3: 650 | F3: =D3*E3 -> 650
A4: 2.0 | B4: LEVANTAMENTO TOPOGRÁFICO E INSUMOS DE CAMPO
A5: 2.1 | B5: Levantamento Territorial Cadastral do Limites Georreferenciado por receptores geodésicos de posicionamento por satélite (GNSS) de Dupla frequecia pelo método relativo estático rápido ou stop-go/NTRIP /RTK para pontos de apoio ou para levantar os limites legais (naturais e artificiais do imóvel) para atendimento Manual Técnico para Georreferenciamento de Imóveis Rurais -MTGIR - 2ª Edição. | C5: hectares | D5: 100 | E5: 35 | F5: =D5*E5 -> 3500
A6: 2.2 | B6: Implantação de Marcos Padrão INCRA com codificação dos vertices e do credenciado | C6: Und | D6: 2 | E6: 150 | F6: =D6*E6 -> 300
A7: 3.0 | B7: ESCRITÓRIO
A8: 3.1 | B8: Elaboração de plantas e peças técnicas em CAD e calculos e memoriais descritivos necessários com impressão em formato ABNT em 3 vias com a elaboração do memorial descritivo, com Anotação de Responsabilidade Técnica - ART | C8: VERBA | D8: 1 | E8: 700 | F8: =D8*E8 -> 700
A9: 3.2 | B9: Elaboração de Planilha ODS para inserção no SIGEF com a Devida Responsabilidade Técnica conforme MTGIR 2° Edição e Lançamento no SIGEF | C9: VERBA | D9: 1 | E9: 500 | F9: =D9*E9 -> 500
A10: 3.3 | B10: Elaboração e Registro do Imóvel no Cadastro Ambiental Rural - CAR no SICAR | C10: VERBA | D10: 1 | E10: 400 | F10: =D10*E10 -> 400
A11: 4.0 | B11: SERVIÇOS DE DESPACHANTE IMOBILIÁRIO
A12: 4.1 | B12: Criação e Registro do Sistma Nacional de Cadastro de Imóvel Rural SNCR para Emissão anual de CCIR ( Area Geral, Remanescente e Desmebrada) | C12: VERBA | D12: 1 | E12: 600 | F12: 500
A13: 4.2 | B13: Criação e Registro do Cadastro de Imóvel do Brasil - CIB na Receita Federal do Brasil | C13: VERBA | D13: 1 | E13: 500 | F13: =D13*E13 -> 500
A14: 4.3 | B14: Regularição o Imposto Territorial Rural - ITR e necessidade de Despachante | C14: VERBA | D14: 1 | E14: 500 | F14: =D14*E14 -> 500
B16: TOTAL | F16: =SUM(F2:F15) -> 7550
B20: DESPESAS:
B21: Marcos | C21: 150
B22: Ajudante | C22: 160
B23: Alimentação | C23: 90
B24: combustivel | C24: 100
C25: 700

Sheet ITEM 10
A1: ITENS | B1: DESCRIÇÃO | C1: UND | D1: QUANT | E1: PREÇO UNIT | F1: PREÇO
A2: 1.0 | B2: MOBILIZAÇÃO
A3: 1.1 | B3: Mobilização de equipamentos e pessoas para realização do levantamento | C3: VERBA | D3: 1 | E3: 650 | F3: =D3*E3 -> 650
A4: 2.0 | B4: LEVANTAMENTO TOPOGRÁFICO E INSUMOS DE CAMPO
A5: 2.1 | B5: Levantamento Territorial Cadastral do Limites Georreferenciado por receptores geodésicos de posicionamento por satélite (GNSS) de Dupla frequecia pelo método relativo estático rápido ou stop-go/NTRIP /RTK para pontos de apoio ou para levantar os limites legais (naturais e artificiais do imóvel) para atendimento Manual Técnico para Georreferenciamento de Imóveis Rurais -MTGIR - 2ª Edição. | C5: hectares | D5: 120 | E5: 35 | F5: =D5*E5 -> 4200
A6: 2.2 | B6: Implantação de Marcos Padrão INCRA com codificação dos vertices e do credenciado | C6: Und | D6: 2 | E6: 150 | F6: =D6*E6 -> 300
A7: 3.0 | B7: ESCRITÓRIO
A8: 3.1 | B8: Elaboração de plantas e peças técnicas em CAD e calculos e memoriais descritivos necessários com impressão em formato ABNT em 3 vias com a elaboração do memorial descritivo, com Anotação de Responsabilidade Técnica - ART | C8: VERBA | D8: 1 | E8: 700 | F8: =D8*E8 -> 700
A9: 3.2 | B9: Elaboração de Planilha ODS para inserção no SIGEF com a Devida Responsabilidade Técnica conforme MTGIR 2° Edição e Lançamento no SIGEF | C9: VERBA | D9: 1 | E9: 500 | F9: =D9*E9 -> 500
A10: 3.3 | B10: Elaboração e Registro do Imóvel no Cadastro Ambiental Rural - CAR no SICAR | C10: VERBA | D10: 1 | E10: 400 | F10: =D10*E10 -> 400
A11: 4.0 | B11: SERVIÇOS DE DESPACHANTE IMOBILIÁRIO
A12: 4.1 | B12: Criação e Registro do Sistma Nacional de Cadastro de Imóvel Rural SNCR para Emissão anual de CCIR ( Area Geral, Remanescente e Desmebrada) | C12: VERBA | D12: 1 | E12: 600 | F12: 500
A13: 4.2 | B13: Criação e Registro do Cadastro de Imóvel do Brasil - CIB na Receita Federal do Brasil | C13: VERBA | D13: 1 | E13: 500 | F13: =D13*E13 -> 500
A14: 4.3 | B14: Regularição o Imposto Territorial Rural - ITR e necessidade de Despachante | C14: VERBA | D14: 1 | E14: 500 | F14: =D14*E14 -> 500
B16: TOTAL | F16: =SUM(F2:F15) -> 8250
B20: DESPESAS:
B21: Marcos | C21: 150
B22: Ajudante | C22: 160
B23: Alimentação | C23: 90
B24: combustivel | C24: 100
C25: 1000

Sheet ITEM 11
A1: ITENS | B1: DESCRIÇÃO | C1: UND | D1: QUANT | E1: PREÇO UNIT | F1: PREÇO
A2: 1.0 | B2: MOBILIZAÇÃO
A3: 1.1 | B3: Mobilização de equipamentos e pessoas para realização do levantamento | C3: VERBA | D3: 1 | E3: 650 | F3: =D3*E3 -> 650
A4: 2.0 | B4: LEVANTAMENTO TOPOGRÁFICO E INSUMOS DE CAMPO
A5: 2.1 | B5: Levantamento Territorial Cadastral do Limites Georreferenciado por receptores geodésicos de posicionamento por satélite (GNSS) de Dupla frequecia pelo método relativo estático rápido ou stop-go/NTRIP /RTK para pontos de apoio ou para levantar os limites legais (naturais e artificiais do imóvel) para atendimento Manual Técnico para Georreferenciamento de Imóveis Rurais -MTGIR - 2ª Edição. | C5: hectares | D5: 10 | E5: 25 | F5: =D5*E5 -> 250
A6: 2.2 | B6: Implantação de Marcos Padrão INCRA com codificação dos vertices e do credenciado | C6: Und | D6: 2 | E6: 150 | F6: =D6*E6 -> 300
A7: 3.0 | B7: ESCRITÓRIO
A8: 3.1 | B8: Elaboração de plantas e peças técnicas em CAD e calculos e memoriais descritivos necessários com impressão em formato ABNT em 3 vias com a elaboração do memorial descritivo, com Anotação de Responsabilidade Técnica - ART | C8: VERBA | D8: 1 | E8: 700 | F8: =D8*E8 -> 700
A9: 3.2 | B9: Elaboração de Planilha ODS para inserção no SIGEF com a Devida Responsabilidade Técnica conforme MTGIR 2° Edição e Lançamento no SIGEF | C9: VERBA | D9: 1 | E9: 500 | F9: =D9*E9 -> 500
A10: 3.3 | B10: Elaboração e Registro do Imóvel no Cadastro Ambiental Rural - CAR no SICAR | C10: VERBA | D10: 1 | E10: 400 | F10: =D10*E10 -> 400
A11: 4.0 | B11: SERVIÇOS DE DESPACHANTE IMOBILIÁRIO
A12: 4.1 | B12: Criação e Registro do Sistma Nacional de Cadastro de Imóvel Rural SNCR para Emissão anual de CCIR ( Area Geral, Remanescente e Desmebrada) | C12: VERBA | D12: 1 | E12: 600 | F12: 500
A13: 4.2 | B13: Criação e Registro do Cadastro de Imóvel do Brasil - CIB na Receita Federal do Brasil | C13: VERBA | D13: 1 | E13: 500 | F13: =D13*E13 -> 500
A14: 4.3 | B14: Regularição o Imposto Territorial Rural - ITR e necessidade de Despachante | C14: VERBA | D14: 1 | E14: 500 | F14: =D14*E14 -> 500
B16: TOTAL | F16: =SUM(F2:F15) -> 4300
B20: DESPESAS:
B21: Marcos | C21: 150
B22: Ajudante | C22: 160
B23: Alimentação | C23: 90
B24: combustivel | C24: 100
C25: 500

Sheet ITENS 12
A1: ITENS | B1: DESCRIÇÃO | C1: UND | D1: QUANT | E1: PREÇO UNIT | F1: PREÇO
A2: 1.0 | B2: MOBILIZAÇÃO
A3: 1.1 | B3: Mobilização de equipamentos e pessoas para realização do levantamento | C3: VERBA | D3: 1 | E3: 650 | F3: =D3*E3 -> 650
A4: 2.0 | B4: LEVANTAMENTO TOPOGRÁFICO E INSUMOS DE CAMPO
A5: 2.1 | B5: Levantamento Territorial Cadastral do Limites Georreferenciado por receptores geodésicos de posicionamento por satélite (GNSS) de Dupla frequecia pelo método relativo estático rápido ou stop-go/NTRIP /RTK para pontos de apoio ou para levantar os limites legais (naturais e artificiais do imóvel) para atendimento Manual Técnico para Georreferenciamento de Imóveis Rurais -MTGIR - 2ª Edição. | C5: hectares | D5: 5.6 | E5: 25 | F5: =D5*E5 -> 140
A6: 2.2 | B6: Implantação de Marcos Padrão INCRA com codificação dos vertices e do credenciado | C6: Und | D6: 2 | E6: 150 | F6: =D6*E6 -> 300
A7: 3.0 | B7: ESCRITÓRIO
A8: 3.1 | B8: Elaboração de plantas e peças técnicas em CAD e calculos e memoriais descritivos necessários com impressão em formato ABNT em 3 vias com a elaboração do memorial descritivo, com Anotação de Responsabilidade Técnica - ART | C8: VERBA | D8: 1 | E8: 700 | F8: =D8*E8 -> 700
A9: 3.2 | B9: Elaboração de Planilha ODS para inserção no SIGEF com a Devida Responsabilidade Técnica conforme MTGIR 2° Edição e Lançamento no SIGEF | C9: VERBA | D9: 1 | E9: 500 | F9: =D9*E9 -> 500
A10: 3.3 | B10: Elaboração e Registro do Imóvel no Cadastro Ambiental Rural - CAR no SICAR | C10: VERBA | D10: 1 | E10: 400 | F10: =D10*E10 -> 400
A11: 4.0 | B11: SERVIÇOS DE DESPACHANTE IMOBILIÁRIO
A12: 4.1 | B12: Criação e Registro do Sistma Nacional de Cadastro de Imóvel Rural SNCR para Emissão anual de CCIR ( Area Geral, Remanescente e Desmebrada) | C12: VERBA | D12: 1 | E12: 600 | F12: 500
A13: 4.2 | B13: Criação e Registro do Cadastro de Imóvel do Brasil - CIB na Receita Federal do Brasil | C13: VERBA | D13: 1 | E13: 500 | F13: =D13*E13 -> 500
A14: 4.3 | B14: Regularição o Imposto Territorial Rural - ITR e necessidade de Despachante | C14: VERBA | D14: 1 | E14: 500 | F14: =D14*E14 -> 500
B16: TOTAL | F16: =SUM(F2:F15) -> 4190
B20: DESPESAS:
B21: Marcos | C21: 150
B22: Ajudante | C22: 160
B23: Alimentação | C23: 90
B24: combustivel | C24: 100
C25: 500

Sheet ITEM13
A1: ITENS | B1: DESCRIÇÃO | C1: UND | D1: QUANT | E1: PREÇO UNIT | F1: PREÇO
A2: 1.0 | B2: MOBILIZAÇÃO
A3: 1.1 | B3: Mobilização de equipamentos e pessoas para realização do levantamento | C3: VERBA | D3: 1 | E3: 650 | F3: =D3*E3 -> 650
A4: 2.0 | B4: LEVANTAMENTO TOPOGRÁFICO E INSUMOS DE CAMPO
A5: 2.1 | B5: Levantamento Territorial Cadastral do Limites Georreferenciado por receptores geodésicos de posicionamento por satélite (GNSS) de Dupla frequecia pelo método relativo estático rápido ou stop-go/NTRIP /RTK para pontos de apoio ou para levantar os limites legais (naturais e artificiais do imóvel) para atendimento Manual Técnico para Georreferenciamento de Imóveis Rurais -MTGIR - 2ª Edição. | C5: hectares | D5: 3 | E5: 25 | F5: =D5*E5 -> 75
A6: 2.2 | B6: Implantação de Marcos Padrão INCRA com codificação dos vertices e do credenciado | C6: Und | D6: 2 | E6: 150 | F6: =D6*E6 -> 300
A7: 3.0 | B7: ESCRITÓRIO
A8: 3.1 | B8: Elaboração de plantas e peças técnicas em CAD e calculos e memoriais descritivos necessários com impressão em formato ABNT em 3 vias com a elaboração do memorial descritivo, com Anotação de Responsabilidade Técnica - ART | C8: VERBA | D8: 1 | E8: 700 | F8: =D8*E8 -> 700
A9: 3.2 | B9: Elaboração de Planilha ODS para inserção no SIGEF com a Devida Responsabilidade Técnica conforme MTGIR 2° Edição e Lançamento no SIGEF | C9: VERBA | D9: 1 | E9: 500 | F9: =D9*E9 -> 500
A10: 3.3 | B10: Elaboração e Registro do Imóvel no Cadastro Ambiental Rural - CAR no SICAR | C10: VERBA | D10: 1 | E10: 400 | F10: =D10*E10 -> 400
A11: 4.0 | B11: SERVIÇOS DE DESPACHANTE IMOBILIÁRIO
A12: 4.1 | B12: Criação e Registro do Sistma Nacional de Cadastro de Imóvel Rural SNCR para Emissão anual de CCIR ( Area Geral, Remanescente e Desmebrada) | C12: VERBA | D12: 1 | E12: 600 | F12: 500
A13: 4.2 | B13: Criação e Registro do Cadastro de Imóvel do Brasil - CIB na Receita Federal do Brasil | C13: VERBA | D13: 1 | E13: 500 | F13: =D13*E13 -> 500
A14: 4.3 | B14: Regularição o Imposto Territorial Rural - ITR e necessidade de Despachante | C14: VERBA | D14: 1 | E14: 500 | F14: =D14*E14 -> 500
B16: TOTAL | F16: =SUM(F2:F15) -> 4125
B20: DESPESAS:
B21: Marcos | C21: 150
B22: Ajudante | C22: 160
B23: Alimentação | C23: 90
B24: combustivel | C24: 100
C25: 500

Sheet ITEM 14
A1: ITENS | B1: DESCRIÇÃO | C1: UND | D1: QUANT | E1: PREÇO UNIT | F1: PREÇO
A2: 1.0 | B2: MOBILIZAÇÃO
A3: 1.1 | B3: Mobilização de equipamentos e pessoas para realização do levantamento | C3: VERBA | D3: 1 | E3: 650 | F3: =D3*E3 -> 650
A4: 2.0 | B4: LEVANTAMENTO TOPOGRÁFICO E INSUMOS DE CAMPO
A5: 2.1 | B5: Levantamento Territorial Cadastral do Limites Georreferenciado por receptores geodésicos de posicionamento por satélite (GNSS) de Dupla frequecia pelo método relativo estático rápido ou stop-go/NTRIP /RTK para pontos de apoio ou para levantar os limites legais (naturais e artificiais do imóvel) para atendimento Manual Técnico para Georreferenciamento de Imóveis Rurais -MTGIR - 2ª Edição. | C5: hectares | D5: 77.5 | E5: 25 | F5: =D5*E5 -> 1937.5
A6: 2.2 | B6: Implantação de Marcos Padrão INCRA com codificação dos vertices e do credenciado | C6: Und | D6: 2 | E6: 150 | F6: =D6*E6 -> 300
A7: 3.0 | B7: ESCRITÓRIO
A8: 3.1 | B8: Elaboração de plantas e peças técnicas em CAD e calculos e memoriais descritivos necessários com impressão em formato ABNT em 3 vias com a elaboração do memorial descritivo, com Anotação de Responsabilidade Técnica - ART | C8: VERBA | D8: 1 | E8: 700 | F8: =D8*E8 -> 700
A9: 3.2 | B9: Elaboração de Planilha ODS para inserção no SIGEF com a Devida Responsabilidade Técnica conforme MTGIR 2° Edição e Lançamento no SIGEF | C9: VERBA | D9: 1 | E9: 500 | F9: =D9*E9 -> 500
A10: 3.3 | B10: Elaboração e Registro do Imóvel no Cadastro Ambiental Rural - CAR no SICAR | C10: VERBA | D10: 1 | E10: 400 | F10: =D10*E10 -> 400
A11: 4.0 | B11: SERVIÇOS DE DESPACHANTE IMOBILIÁRIO
A12: 4.1 | B12: Criação e Registro do Sistma Nacional de Cadastro de Imóvel Rural SNCR para Emissão anual de CCIR ( Area Geral, Remanescente e Desmebrada) | C12: VERBA | D12: 1 | E12: 600 | F12: 500
A13: 4.2 | B13: Criação e Registro do Cadastro de Imóvel do Brasil - CIB na Receita Federal do Brasil | C13: VERBA | D13: 1 | E13: 500 | F13: =D13*E13 -> 500
A14: 4.3 | B14: Regularição o Imposto Territorial Rural - ITR e necessidade de Despachante | C14: VERBA | D14: 1 | E14: 500 | F14: =D14*E14 -> 500
B16: TOTAL | F16: =SUM(F2:F15) -> 5987.5
B20: DESPESAS:
B21: Marcos | C21: 150
B22: Ajudante | C22: 160
B23: Alimentação | C23: 90
B24: combustivel | C24: 100
C25: 1200

Sheet ITEM15
A1: ITENS | B1: DESCRIÇÃO | C1: UND | D1: QUANT | E1: PREÇO UNIT | F1: PREÇO
A2: 1.0 | B2: MOBILIZAÇÃO
A3: 1.1 | B3: Mobilização de equipamentos e pessoas para realização do levantamento | C3: VERBA | D3: 1 | E3: 650 | F3: =D3*E3 -> 650
A4: 2.0 | B4: LEVANTAMENTO TOPOGRÁFICO E INSUMOS DE CAMPO
A5: 2.1 | B5: Levantamento Territorial Cadastral do Limites Georreferenciado por receptores geodésicos de posicionamento por satélite (GNSS) de Dupla frequecia pelo método relativo estático rápido ou stop-go/NTRIP /RTK para pontos de apoio ou para levantar os limites legais (naturais e artificiais do imóvel) para atendimento Manual Técnico para Georreferenciamento de Imóveis Rurais -MTGIR - 2ª Edição. | C5: hectares | D5: 135 | E5: 35 | F5: =D5*E5 -> 4725
A6: 2.2 | B6: Implantação de Marcos Padrão INCRA com codificação dos vertices e do credenciado | C6: Und | D6: 2 | E6: 150 | F6: =D6*E6 -> 300
A7: 3.0 | B7: ESCRITÓRIO
A8: 3.1 | B8: Elaboração de plantas e peças técnicas em CAD e calculos e memoriais descritivos necessários com impressão em formato ABNT em 3 vias com a elaboração do memorial descritivo, com Anotação de Responsabilidade Técnica - ART | C8: VERBA | D8: 1 | E8: 700 | F8: =D8*E8 -> 700
A9: 3.2 | B9: Elaboração de Planilha ODS para inserção no SIGEF com a Devida Responsabilidade Técnica conforme MTGIR 2° Edição e Lançamento no SIGEF | C9: VERBA | D9: 1 | E9: 500 | F9: =D9*E9 -> 500
A10: 3.3 | B10: Elaboração e Registro do Imóvel no Cadastro Ambiental Rural - CAR no SICAR | C10: VERBA | D10: 1 | E10: 400 | F10: =D10*E10 -> 400
A11: 4.0 | B11: SERVIÇOS DE DESPACHANTE IMOBILIÁRIO
A12: 4.1 | B12: Criação e Registro do Sistma Nacional de Cadastro de Imóvel Rural SNCR para Emissão anual de CCIR ( Area Geral, Remanescente e Desmebrada) | C12: VERBA | D12: 1 | E12: 600 | F12: 500
A13: 4.2 | B13: Criação e Registro do Cadastro de Imóvel do Brasil - CIB na Receita Federal do Brasil | C13: VERBA | D13: 1 | E13: 500 | F13: =D13*E13 -> 500
A14: 4.3 | B14: Regularição o Imposto Territorial Rural - ITR e necessidade de Despachante | C14: VERBA | D14: 1 | E14: 500 | F14: =D14*E14 -> 500
B16: TOTAL | F16: =SUM(F2:F15) -> 8775
B20: DESPESAS:
B21: Marcos | C21: 150
B22: Ajudante | C22: 160
B23: Alimentação | C23: 90
B24: combustivel | C24: 100
C25: 500

Sheet ITEM16
A1: ITENS | B1: DESCRIÇÃO | C1: UND | D1: QUANT | E1: PREÇO UNIT | F1: PREÇO
A2: 1.0 | B2: MOBILIZAÇÃO
A3: 1.1 | B3: Mobilização de equipamentos e pessoas para realização do levantamento | C3: VERBA | D3: 1 | E3: 650 | F3: =D3*E3 -> 650
A4: 2.0 | B4: LEVANTAMENTO TOPOGRÁFICO E INSUMOS DE CAMPO
A5: 2.1 | B5: Levantamento Territorial Cadastral do Limites Georreferenciado por receptores geodésicos de posicionamento por satélite (GNSS) de Dupla frequecia pelo método relativo estático rápido ou stop-go/NTRIP /RTK para pontos de apoio ou para levantar os limites legais (naturais e artificiais do imóvel) para atendimento Manual Técnico para Georreferenciamento de Imóveis Rurais -MTGIR - 2ª Edição. | C5: hectares | D5: 135 | E5: 35 | F5: =D5*E5 -> 4725
A6: 2.2 | B6: Implantação de Marcos Padrão INCRA com codificação dos vertices e do credenciado | C6: Und | D6: 2 | E6: 150 | F6: =D6*E6 -> 300
A7: 3.0 | B7: ESCRITÓRIO
A8: 3.1 | B8: Elaboração de plantas e peças técnicas em CAD e calculos e memoriais descritivos necessários com impressão em formato ABNT em 3 vias com a elaboração do memorial descritivo, com Anotação de Responsabilidade Técnica - ART | C8: VERBA | D8: 1 | E8: 700 | F8: =D8*E8 -> 700
A9: 3.2 | B9: Elaboração de Planilha ODS para inserção no SIGEF com a Devida Responsabilidade Técnica conforme MTGIR 2° Edição e Lançamento no SIGEF | C9: VERBA | D9: 1 | E9: 500 | F9: =D9*E9 -> 500
A10: 3.3 | B10: Elaboração e Registro do Imóvel no Cadastro Ambiental Rural - CAR no SICAR | C10: VERBA | D10: 1 | E10: 400 | F10: =D10*E10 -> 400
A11: 4.0 | B11: SERVIÇOS DE DESPACHANTE IMOBILIÁRIO
A12: 4.1 | B12: Criação e Registro do Sistma Nacional de Cadastro de Imóvel Rural SNCR para Emissão anual de CCIR ( Area Geral, Remanescente e Desmebrada) | C12: VERBA | D12: 1 | E12: 600 | F12: 500
A13: 4.2 | B13: Criação e Registro do Cadastro de Imóvel do Brasil - CIB na Receita Federal do Brasil | C13: VERBA | D13: 1 | E13: 500 | F13: =D13*E13 -> 500
A14: 4.3 | B14: Regularição o Imposto Territorial Rural - ITR e necessidade de Despachante | C14: VERBA | D14: 1 | E14: 500 | F14: =D14*E14 -> 500
B16: TOTAL | F16: =SUM(F2:F15) -> 8775
B20: DESPESAS:
B21: Marcos | C21: 150
B22: Ajudante | C22: 160
B23: Alimentação | C23: 90
B24: combustivel | C24: 100
C25: 500

Sheet RESUMO
A2: ITENS | B2: ÁREAS | C2: VALOR(R$) | D2: REDUÇÃO | F2: REDUZIR | G2: TOTAL
A3: 1 | B3: ='ITEM 01'!D5 -> 90.5 | C3: ='ITEM 01'!F16 -> 7217.5 | D3: 600 | E3: =C3-D3 -> 6617.5 | F3: 2500 | G3: =E3-F3 -> 4117.5
A4: 2 | B4: 9 | C4: ='ITEM 02'!F16 -> 4275 | D4: 600 | E4: =C4-D4 -> 3675 | F4: 2500 | G4: =E4-F4 -> 1175
A5: 3 | B5: 3.2 | C5: ='ITEM 03'!F16 -> 5057.5 | D5: 600 | E5: =C5-D5 -> 4457.5 | F5: 2500 | G5: =E5-F5 -> 1957.5
A6: 4 | B6: ='ITEM 03'!D5 -> 40.3 | C6: ='ITEM 04'!F16 -> 5057.5 | D6: 600 | E6: =C6-D6 -> 4457.5 | F6: 2500 | G6: =E6-F6 -> 1957.5
A7: 5 | B7: ='ITEM 05'!D5 -> 9 | C7: ='ITEM 05'!F16 -> 4275 | D7: 600 | E7: =C7-D7 -> 3675 | F7: 2500 | G7: =E7-F7 -> 1175
A8: 6 | B8: ='ITEM 06'!D5 -> 7 | C8: ='ITEM 06'!F16 -> 4225 | D8: 600 | E8: =C8-D8 -> 3625 | F8: 2500 | G8: =E8-F8 -> 1125
A9: 7 | B9: =ITEM07!D5 -> 1.8 | C9: =ITEM07!F16 -> 4095 | D9: 600 | E9: =C9-D9 -> 3495 | F9: 2500 | G9: =E9-F9 -> 995
A10: 8 | B10: ='ITEM 08'!D5 -> 3.6 | C10: ='ITEM 08'!F16 -> 4140 | D10: 600 | E10: =C10-D10 -> 3540 | F10: 2500 | G10: =E10-F10 -> 1040
A11: 9 | B11: ='ITEM 09'!D5 -> 100 | C11: ='ITEM 09'!F16 -> 7550 | D11: 600 | E11: =C11-D11 -> 6950 | F11: 2500 | G11: =E11-F11 -> 4450
A12: 10 | B12: 20 | C12: ='ITEM 10'!F16 -> 8250 | D12: 600 | E12: =C12-D12 -> 7650 | F12: 2500 | G12: =E12-F12 -> 5150
A13: 11 | B13: ='ITEM 11'!D5 -> 10 | C13: ='ITEM 11'!F16 -> 4300 | D13: 600 | E13: =C13-D13 -> 3700 | F13: 2500 | G13: =E13-F13 -> 1200
A14: 12 | B14: ='ITENS 12'!D5 -> 5.6 | C14: ='ITENS 12'!F16 -> 4190 | D14: 600 | E14: =C14-D14 -> 3590 | F14: 2500 | G14: =E14-F14 -> 1090
A15: 13 | B15: 4 | C15: =ITEM13!F16 -> 4125 | D15: 600 | E15: =C15-D15 -> 3525 | F15: 2500 | G15: =E15-F15 -> 1025
A16: 14 | B16: ='ITEM 14'!D5 -> 77.5 | C16: ='ITEM 14'!F16 -> 5987.5 | D16: 600 | E16: =C16-D16 -> 5387.5 | F16: 2500 | G16: =E16-F16 -> 2887.5
A17: 15 | B17: 1.36 | C17: =ITEM15!F16 -> 8775 | D17: 600 | E17: =C17-D17 -> 8175 | F17: 2500 | G17: =E17-F17 -> 5675
A18: TOTAL | B18: =SUM(B3:B17) -> 382.86 | E18: =SUM(E3:E17) -> 72520 | G18: =SUM(G3:G17) -> 35020 | H18: =G18/B18 -> 91.469467
C22: 382.86 | D22: 35 | E22: =C22*D22 -> 13400.1
D24: =18000/C22 -> 47.014575
