Workbook

Sheet GERAL
A1: CCIR | B1: NOME | C1: MUNICIPIO | D1: UF | E1: ÁREA (HA) | F1: CPF/CNPJ | G1: NOME | H1: VALOR DO SERVIÇO
A2: 950.165.587.443-9 | B2: GRANJA BELO HORIZONTE | C2: CARPINA | D2: PE | E2: 20 | F2: 19.285/080/0001-05 | G2: SANTOS AVICULTURA LTDA | H2: ='GRANJA BELO HORIZONTE'!F14 -> 3600
A3: 227.080.005.827-3 | B3: FAZENDA GAMALEIRA | C3: LIMOEIRO | D3: PE | E3: 128 | F3: 19.285.080/0001-05 | G3: SANTOS AVICULTURA LTDA | H3: ='FAZENDA GAMALEIRA'!F14 -> 5950
A4: 950.017.522.430-6 | B4: LOTE 39 | C4: PAUDALHO | D4: PE | E4: 3.5 | F4: 665.959.914-20 | G4: EDILSON DE ARAUJO SANTOS JUNIOR | H4: ='LOTE 39'!F14 -> 2637.5
A5: 230.154.001.805-4 | B5: PROPRIEDADE JARDIM | C5: PAUDALHO | D5: PE | E5: 20.9 | F5: 665.959.914-20 | G5: EDILSON DE ARAUJO SANTOS JUNIOR | H5: ='PROPRIEDADE JARDIM'!F14 -> 3072.5
A6: 230.154.253.766-0 | B6: GRANJA NOVO NORTE | C6: PAUDALHO | D6: PE | E6: 32 | F6: 665.959.914-20 | G6: EDILSON DE ARAUJO SANTOS JUNIOR | H6: ='GRANJA NOVO NORTE'!F14 -> 3350
A7: 230.154.001.970-0 | B7: GRANJA PALACINHO | C7: PAUDALHO | D7: PE | E7: 11.8 | F7: 021.398.394-04 | G7: EDILSON DE ARAUJO SANTOS | H7: ='GRANJA PALACINHO'!F14 -> 2845
A8: 230.154.001.813-5 | B8: SITIO BELEM | C8: PAUDALHO | D8: PE | E8: 14 | F8: 665.959.834-00 | G8: PAULO HENRIQUE BORGES SANTOS | H8: ='SÍTIO BELÉM'!F14 -> 2900
A9: 230.154.000.043-0 | B9: SIÂ-TIO BELEM | C9: PAUDALHO | D9: PE | E9: 10 | F9: 665.959.914-20 | G9: EDILSON DE ARAUJO SANTOS JUNIOR | H9: ='SIÂ-TIO BELEM'!F14 -> 2900
A10: 950.165.343.617-5 | B10: GRANJA PALACETE | C10: PAUDALHO | D10: PE | E10: 58 | F10: 19.285.080/0001-05 | G10: SANTOS AVICULTURA LTDA | H10: ='GRANJA PALACETE'!F14 -> 2900
A11: 230.154.002.895-5 | B11: GRANJA GRANJITA | C11: PAUDALHO | D11: PE | E11: 63.9 | F11: 665.959.914-20 | G11: EDILSON DE ARAUJO SANTOS JUNIOR | H11: ='GRANJA GRANJITA'!F14 -> 2500
A12: 950.114.827.444-6 | B12: GRANJA SÃO LUIS | C12: PAUDALHO | D12: PE | E12: 28.9 | F12: 19.285.080/0001-05 | G12: SANTOS AVICULTURA LTDA | H12: ='GRANJA SÃO LUIS'!F14 -> 3272.5
A13: 230.154.002.119-5 | B13: GRANJA SANTA ELIZIA I | C13: PAUDALHO | D13: PE | E13: 13.9 | F13: 665.959.914-20 | G13: EDILSON DE ARAUJO SANTOS JUNIOR | H13: ='GRANJA SANTA ELIZIA I'!F14 -> 1397.5
A14: 951.072.167.550-6 | B14: FAZENDA VARZEA VERDE II | C14: SÃO CRISTOVAO | D14: SE | E14: 31.1 | F14: 19.285.080/0001-05 | G14: SANTOS AVICULTURA LTDA | H14: ='FAZENDA VARZEA VERDE II'!F14 -> 5155
A15: 267.082.008.028-1 | B15: GRANJA PITANGA | C15: SÃO CRISTOVAO | D15: SE | E15: 121 | F15: 021.398.394-04 | G15: EDILSON DE ARAUJO SANTOS | H15: ='GRANJA PITANGA'!F14 -> 5155
A16: 265.055.023.280-6 | B16: FAZENDA NOSSA SENHORA DE FATIMA | C16: SÃO CRISTOVAO | D16: SE | E16: 25.1 | F16: 021.398.394-04 | G16: EDILSON DE ARAUJO SANTOS | H16: ='FAZENDA NOSSA SENHORA DE FATIMA'!F14 -> 5155
A17: 999.911.232.807-6 | B17: GRANJA HORTA VELHA | C17: SÃO CRISTOVAO | D17: SE | E17: 20.2 | F17: 021.398.394-04 | G17: EDILSON DE ARAUJO SANTOS | H17: ='GRANJA HORTA VELHA'!F14 -> 4610
A18: 950.238.444.677-7 | B18: GRANJA SANTO ANTONIO | C18: PAUDALHO | D18: PE | E18: 8.8951 | F18: 19.285.080/0001-05 | G18: SANTOS AVICULTURA LTDA | H18: ='GRANJA SANTO ANTONIO'!F14 -> 2772.3775
A19: 950.238.444.057-4 | B19: GRANJA SAO JUDAS TADEU | C19: PAUDALHO | D19: PE | E19: 8.066 | F19: 19.285.080/0001-05 | G19: SANTOS AVICULTURA LTDA | H19: ='GRANJA SAO JUDAS TADEU'!F14 -> 2751.65
A20: 950.165.604.747-1 | B20: GRANJA GAVIAO | C20: PAUDALHO | D20: PE | E20: 8.84 | F20: 19.285.080/0001-05 | G20: SANTOS AVICULTURA LTDA | H20: ='GRANJA GAVIAO'!F14 -> 2771
A21: 950.254.138.347-4 | B21: GRANJA HERCULANO BANDEIRA PARTE 1 | C21: PAUDALHO | D21: PE | E21: 5.9527 | F21: 19.285.080/0001-05 | G21: SANTOS AVICULTURA LTDA | H21: ='GRANJA HERCULANO BANDEIRA PARTE'!F14 -> 2698.75
A22: 950.149.729.949-9 | B22: GRANJA SIMMENTEL | C22: PAUDALHO | D22: PE | E22: 10 | F22: 075.105.604-97 | G22: PETER HAGER | H22: ='GRANJA SIMMENTEL'!F14 -> 2800
H23: =SUM(H2:H22) -> 71193.777

Sheet GRANJA BELO HORIZONTE
A1: ITENS | B1: DESCRIÇÃO | C1: UND | D1: QUANT. | E1: PREÇO | F1: VALOR
E2: UNITÁRIIO | F2: VALOR
A3: 1.0 | B3: Mobilização
A4: 1.1 | B4: Mobilização de equipamentos e pessoas para realização do levantamento para adquação do levantamento para atender as especificações do Manual de Georreferenciamento (MTGIR, 2022) | C4: VERBA | D4: 1 | E4: 500 | F4: =D4*E4 -> 500
A5: 2.0 | B5: Levantamento Cadastral Territorial (campo e Escritòrio)
A6: 2.3 | B6: Confecção e Implantação de Marcos e plaquetas Padrão INCRA. | C6: UNID | D6: 2 | E6: 75 | F6: =D6*E6 -> 150
A7: 2.2 | B7: Serviços de campo para medição e Georreferenciamento dos vértices definidores do perímetro total conforme estabelece o Manual Técnico de Georrferenciamendo Imóveis Rurais 2022. | C7: hectares | D7: 20 | E7: 50 | F7: =D7*E7 -> 1000
A8: 2.4 | B8: Serviços de Gabinete: processamento e analise de dados, elaboração de planilhas eletrônicas, relatórios, cálculos e Geração de Planilhas ODS para Certificação | C8: verba | D8: 1 | E8: 250 | F8: =D8*E8 -> 250
A9: 2.6 | B9: Elaboração de planta em CAD e calculos necessários com impressão em formato ABNT em 3 vias com a elaboração do memorial descritivo, com Registro de ART junto ao CREA, Honorários de responsabilidade técnica e consultoria. | C9: hectares | D9: 1 | E9: 200 | F9: =D9*E9 -> 200 | G9: RECEITA
A10: 2.0 | B10: Despachante Imobiliário
B11: Correção/ atualização do CCIR, registro do CIB e Atualização do CAR | C11: Verba | D11: 1 | E11: 1500 | F11: =D11*E11 -> 1500
B14: Total | F14: =SUM(F3:F13) -> 3600 | G14: =F14-E25 -> 2815
B17: DESPESAS | C17: QUANT | D17: PREÇO | E17: VALOR
B18: ALIMENTAÇÃO | C18: 2 | D18: 50 | E18: =C18*D18 -> 100
B19: HOSPEDAGEM | C19: 0 | D19: 250 | E19: =C19*D19 -> 0
B20: COMBUSTIVEL | C20: 0.5 | D20: 170 | E20: =C20*D20 -> 85
B21: AJUDANTES | C21: 1 | D21: 150 | E21: =C21*D21 -> 150
B22: PLAQUETAS | C22: 5 | D22: 30 | E22: =C22*D22 -> 150
B23: PROCESSAMENTO DOS DADOS | C23: 1 | D23: 150 | E23: =C23*D23 -> 150
B24: JAIRO | C24: 1 | D24: 150 | E24: =C24*D24 -> 150
E25: =SUM(E18:E24) -> 785

Sheet FAZENDA GAMALEIRA
A1: ITENS | B1: DESCRIÇÃO | C1: UND | D1: QUANT. | E1: PREÇO | F1: VALOR
E2: UNITÁRIIO | F2: VALOR
A3: 1.0 | B3: Mobilização
A4: 1.1 | B4: Logistica e Mobilização de equipamentos e pessoas para realização do levantamento para adquação do levantamento para atender as especificações do Manual de Georreferenciamento (MTGIR, 2022) | C4: VERBA | D4: 1 | E4: 650 | F4: =D4*E4 -> 650
A5: 2.0 | B5: Levantamento Cadastral Territorial (campo e Escritòrio)
A6: 2.3 | B6: Confecção e Implantação de Marcos e plaquetas Padrão INCRA. | C6: UNID | D6: 2 | E6: 75 | F6: =D6*E6 -> 150
A7: 2.2 | B7: Serviços de campo para medição e Georreferenciamento dos vértices definidores do perímetro total conforme estabelece o Manual Técnico de Georrferenciamendo Imóveis Rurais 2022. | C7: hectares | D7: 128 | E7: 25 | F7: =D7*E7 -> 3200
A8: 2.4 | B8: Serviços de Gabinete: processamento e analise de dados, elaboração de planilhas eletrônicas, relatórios, cálculos e Geração de Planilhas ODS para Certificação | C8: verba | D8: 1 | E8: 250 | F8: =D8*E8 -> 250
A9: 2.6 | B9: Elaboração de planta em CAD e calculos necessários com impressão em formato ABNT em 3 vias com a elaboração do memorial descritivo, com Registro de ART junto ao CREA, Honorários de responsabilidade técnica e consultoria. | C9: hectares | D9: 1 | E9: 200 | F9: =D9*E9 -> 200 | G9: RECEITA
A10: 2.0 | B10: Despachante Imobiliário
B11: Correção/ atualização do CCIR, registro do CIB e Atualização do CAR | C11: Verba | D11: 1 | E11: 1500 | F11: =D11*E11 -> 1500
B14: Total | F14: =SUM(F3:F13) -> 5950 | G14: =F14-E25 -> 5315
B17: DESPESAS | C17: QUANT | D17: PREÇO | E17: VALOR
B18: ALIMENTAÇÃO | C18: 2 | D18: 50 | E18: =C18*D18 -> 100
B19: HOSPEDAGEM | C19: 0 | D19: 250 | E19: =C19*D19 -> 0
B20: COMBUSTIVEL | C20: 0.5 | D20: 170 | E20: =C20*D20 -> 85
B21: AJUDANTES | C21: 1 | D21: 150 | E21: =C21*D21 -> 150
B22: PLAQUETAS | C22: 5 | D22: 30 | E22: =C22*D22 -> 150
B23: PROCESSAMENTO DOS DADOS | C23: 1 | D23: 150 | E23: =C23*D23 -> 150
E25: =SUM(E18:E24) -> 635

Sheet LOTE 39
A1: ITENS | B1: DESCRIÇÃO | C1: UND | D1: QUANT. | E1: PREÇO | F1: VALOR
E2: UNITÁRIIO | F2: VALOR
A3: 1.0 | B3: Mobilização
A4: 1.1 | B4: Logistica e Mobilização de equipamentos e pessoas para realização do levantamento para adquação do levantamento para atender as especificações do Manual de Georreferenciamento (MTGIR, 2022) | C4: VERBA | D4: 1 | E4: 450 | F4: =D4*E4 -> 450
A5: 2.0 | B5: Levantamento Cadastral Territorial (campo e Escritòrio)
A6: 2.3 | B6: Confecção e Implantação de Marcos e plaquetas Padrão INCRA. | C6: UNID | D6: 2 | E6: 75 | F6: =D6*E6 -> 150
A7: 2.2 | B7: Serviços de campo para medição e Georreferenciamento dos vértices definidores do perímetro total conforme estabelece o Manual Técnico de Georrferenciamendo Imóveis Rurais 2022. | C7: hectares | D7: 3.5 | E7: 25 | F7: =D7*E7 -> 87.5
A8: 2.4 | B8: Serviços de Gabinete: processamento e analise de dados, elaboração de planilhas eletrônicas, relatórios, cálculos e Geração de Planilhas ODS para Certificação | C8: verba | D8: 1 | E8: 250 | F8: =D8*E8 -> 250
A9: 2.6 | B9: Elaboração de planta em CAD e calculos necessários com impressão em formato ABNT em 3 vias com a elaboração do memorial descritivo, com Registro de ART junto ao CREA, Honorários de responsabilidade técnica e consultoria. | C9: hectares | D9: 1 | E9: 200 | F9: =D9*E9 -> 200 | G9: RECEITA
A10: 2.0 | B10: Despachante Imobiliário
B11: Correção/ atualização do CCIR, registro do CIB e Atualização do CAR | C11: Verba | D11: 1 | E11: 1500 | F11: =D11*E11 -> 1500
B14: Total | F14: =SUM(F3:F13) -> 2637.5 | G14: =F14-E25 -> 2002.5
B17: DESPESAS | C17: QUANT | D17: PREÇO | E17: VALOR
B18: ALIMENTAÇÃO | C18: 2 | D18: 50 | E18: =C18*D18 -> 100
B19: HOSPEDAGEM | C19: 0 | D19: 250 | E19: =C19*D19 -> 0
B20: COMBUSTIVEL | C20: 0.5 | D20: 170 | E20: =C20*D20 -> 85
B21: AJUDANTES | C21: 1 | D21: 150 | E21: =C21*D21 -> 150
B22: PLAQUETAS | C22: 5 | D22: 30 | E22: =C22*D22 -> 150
B23: PROCESSAMENTO DOS DADOS | C23: 1 | D23: 150 | E23: =C23*D23 -> 150
E25: =SUM(E18:E24) -> 635

Sheet PROPRIEDADE JARDIM
A1: ITENS | B1: DESCRIÇÃO | C1: UND | D1: QUANT. | E1: PREÇO | F1: VALOR
E2: UNITÁRIIO | F2: VALOR
A3: 1.0 | B3: Mobilização
A4: 1.1 | B4: Logistica e Mobilização de equipamentos e pessoas para realização do levantamento para adquação do levantamento para atender as especificações do Manual de Georreferenciamento (MTGIR, 2022) | C4: VERBA | D4: 1 | E4: 450 | F4: =D4*E4 -> 450
A5: 2.0 | B5: Levantamento Cadastral Territorial (campo e Escritòrio)
A6: 2.3 | B6: Confecção e Implantação de Marcos e plaquetas Padrão INCRA. | C6: UNID | D6: 2 | E6: 75 | F6: =D6*E6 -> 150
A7: 2.2 | B7: Serviços de campo para medição e Georreferenciamento dos vértices definidores do perímetro total conforme estabelece o Manual Técnico de Georrferenciamendo Imóveis Rurais 2022. | C7: hectares | D7: 20.9 | E7: 25 | F7: =D7*E7 -> 522.5
A8: 2.4 | B8: Serviços de Gabinete: processamento e analise de dados, elaboração de planilhas eletrônicas, relatórios, cálculos e Geração de Planilhas ODS para Certificação | C8: verba | D8: 1 | E8: 250 | F8: =D8*E8 -> 250
A9: 2.6 | B9: Elaboração de planta em CAD e calculos necessários com impressão em formato ABNT em 3 vias com a elaboração do memorial descritivo, com Registro de ART junto ao CREA, Honorários de responsabilidade técnica e consultoria. | C9: hectares | D9: 1 | E9: 200 | F9: =D9*E9 -> 200 | G9: RECEITA
A10: 2.0 | B10: Despachante Imobiliário
B11: Correção/ atualização do CCIR, registro do CIB e Atualização do CAR | C11: Verba | D11: 1 | E11: 1500 | F11: =D11*E11 -> 1500
B14: Total | F14: =SUM(F3:F13) -> 3072.5 | G14: =F14-E25 -> 2437.5
B17: DESPESAS | C17: QUANT | D17: PREÇO | E17: VALOR
B18: ALIMENTAÇÃO | C18: 2 | D18: 50 | E18: =C18*D18 -> 100
B19: HOSPEDAGEM | C19: 0 | D19: 250 | E19: =C19*D19 -> 0
B20: COMBUSTIVEL | C20: 0.5 | D20: 170 | E20: =C20*D20 -> 85
B21: AJUDANTES | C21: 1 | D21: 150 | E21: =C21*D21 -> 150
B22: PLAQUETAS | C22: 5 | D22: 30 | E22: =C22*D22 -> 150
B23: PROCESSAMENTO DOS DADOS | C23: 1 | D23: 150 | E23: =C23*D23 -> 150
E25: =SUM(E18:E24) -> 635

Sheet GRANJA NOVO NORTE
A1: ITENS | B1: DESCRIÇÃO | C1: UND | D1: QUANT. | E1: PREÇO | F1: VALOR
E2: UNITÁRIIO | F2: VALOR
A3: 1.0 | B3: Mobilização
A4: 1.1 | B4: Logistica e Mobilização de equipamentos e pessoas para realização do levantamento para adquação do levantamento para atender as especificações do Manual de Georreferenciamento (MTGIR, 2022) | C4: VERBA | D4: 1 | E4: 450 | F4: =D4*E4 -> 450
A5: 2.0 | B5: Levantamento Cadastral Territorial (campo e Escritòrio)
A6: 2.3 | B6: Confecção e Implantação de Marcos e plaquetas Padrão INCRA. | C6: UNID | D6: 2 | E6: 75 | F6: =D6*E6 -> 150
A7: 2.2 | B7: Serviços de campo para medição e Georreferenciamento dos vértices definidores do perímetro total conforme estabelece o Manual Técnico de Georrferenciamendo Imóveis Rurais 2022. | C7: hectares | D7: 32 | E7: 25 | F7: =D7*E7 -> 800
A8: 2.4 | B8: Serviços de Gabinete: processamento e analise de dados, elaboração de planilhas eletrônicas, relatórios, cálculos e Geração de Planilhas ODS para Certificação | C8: verba | D8: 1 | E8: 250 | F8: =D8*E8 -> 250
A9: 2.6 | B9: Elaboração de planta em CAD e calculos necessários com impressão em formato ABNT em 3 vias com a elaboração do memorial descritivo, com Registro de ART junto ao CREA, Honorários de responsabilidade técnica e consultoria. | C9: hectares | D9: 1 | E9: 200 | F9: =D9*E9 -> 200 | G9: RECEITA
A10: 3.0 | B10: Despachante Imobiliário
B11: Correção/ atualização do CCIR, registro do CIB e Atualização do CAR | C11: Verba | D11: 1 | E11: 1500 | F11: =D11*E11 -> 1500
B14: Total | F14: =SUM(F3:F13) -> 3350 | G14: =F14-E25 -> 2665
B17: DESPESAS | C17: QUANT | D17: PREÇO | E17: VALOR
B18: ALIMENTAÇÃO | C18: 2 | D18: 75 | E18: =C18*D18 -> 150
B19: HOSPEDAGEM | C19: 0 | D19: 250 | E19: =C19*D19 -> 0
B20: COMBUSTIVEL | C20: 0.5 | D20: 170 | E20: =C20*D20 -> 85
B21: AJUDANTES | C21: 1 | D21: 150 | E21: =C21*D21 -> 150
B22: PLAQUETAS | C22: 5 | D22: 30 | E22: =C22*D22 -> 150
B23: PROCESSAMENTO DOS DADOS | C23: 1 | D23: 150 | E23: =C23*D23 -> 150
E25: =SUM(E18:E24) -> 685

Sheet GRANJA PALACINHO
A1: ITENS | B1: DESCRIÇÃO | C1: UND | D1: QUANT. | E1: PREÇO | F1: VALOR
E2: UNITÁRIIO | F2: VALOR
A3: 1.0 | B3: Mobilização
A4: 1.1 | B4: Logistica e Mobilização de equipamentos e pessoas para realização do levantamento para adquação do levantamento para atender as especificações do Manual de Georreferenciamento (MTGIR, 2022) | C4: VERBA | D4: 1 | E4: 450 | F4: =D4*E4 -> 450
A5: 2.0 | B5: Levantamento Cadastral Territorial (campo e Escritòrio)
A6: 2.3 | B6: Confecção e Implantação de Marcos e plaquetas Padrão INCRA. | C6: UNID | D6: 2 | E6: 75 | F6: =D6*E6 -> 150
A7: 2.2 | B7: Serviços de campo para medição e Georreferenciamento dos vértices definidores do perímetro total conforme estabelece o Manual Técnico de Georrferenciamendo Imóveis Rurais 2022. | C7: hectares | D7: 11.8 | E7: 25 | F7: =D7*E7 -> 295
A8: 2.4 | B8: Serviços de Gabinete: processamento e analise de dados, elaboração de planilhas eletrônicas, relatórios, cálculos e Geração de Planilhas ODS para Certificação | C8: verba | D8: 1 | E8: 250 | F8: =D8*E8 -> 250
A9: 2.6 | B9: Elaboração de planta em CAD e calculos necessários com impressão em formato ABNT em 3 vias com a elaboração do memorial descritivo, com Registro de ART junto ao CREA, Honorários de responsabilidade técnica e consultoria. | C9: hectares | D9: 1 | E9: 200 | F9: =D9*E9 -> 200 | G9: RECEITA
A10: 2.0 | B10: Despachante Imobiliário
A11: 2.1 | B11: Correção/ atualização do CCIR, registro do CIB e Atualização do CAR | C11: Verba | D11: 1 | E11: 1500 | F11: =D11*E11 -> 1500
A12: ,
B14: Total | F14: =SUM(F3:F13) -> 2845
B17: DESPESAS | C17: QUANT | D17: PREÇO | E17: VALOR
B18: ALIMENTAÇÃO | C18: 2 | D18: 75 | E18: =C18*D18 -> 150
B19: HOSPEDAGEM | C19: 0 | D19: 250 | E19: =C19*D19 -> 0
B20: COMBUSTIVEL | C20: 0.5 | D20: 170 | E20: =C20*D20 -> 85
B21: AJUDANTES | C21: 1 | D21: 150 | E21: =C21*D21 -> 150
B22: PLAQUETAS | C22: 5 | D22: 30 | E22: =C22*D22 -> 150
B23: PROCESSAMENTO DOS DADOS | C23: 1 | D23: 150 | E23: =C23*D23 -> 150
E25: =SUM(E18:E24) -> 685

Sheet SÍTIO BELÉM
A1: ITENS | B1: DESCRIÇÃO | C1: UND | D1: QUANT. | E1: PREÇO | F1: VALOR
E2: UNITÁRIIO | F2: VALOR
A3: 1.0 | B3: Mobilização
A4: 1.1 | B4: Logistica e Mobilização de equipamentos e pessoas para realização do levantamento para adquação do levantamento para atender as especificações do Manual de Georreferenciamento (MTGIR, 2022) | C4: VERBA | D4: 1 | E4: 450 | F4: =D4*E4 -> 450
A5: 2.0 | B5: Levantamento Cadastral Territorial (campo e Escritòrio)
A6: 2.3 | B6: Confecção e Implantação de Marcos e plaquetas Padrão INCRA. | C6: UNID | D6: 2 | E6: 75 | F6: =D6*E6 -> 150
A7: 2.2 | B7: Serviços de campo para medição e Georreferenciamento dos vértices definidores do perímetro total conforme estabelece o Manual Técnico de Georrferenciamendo Imóveis Rurais 2022. | C7: hectares | D7: 14 | E7: 25 | F7: =D7*E7 -> 350
A8: 2.4 | B8: Serviços de Gabinete: processamento e analise de dados, elaboração de planilhas eletrônicas, relatórios, cálculos e Geração de Planilhas ODS para Certificação | C8: verba | D8: 1 | E8: 250 | F8: =D8*E8 -> 250
A9: 2.6 | B9: Elaboração de planta em CAD e calculos necessários com impressão em formato ABNT em 3 vias com a elaboração do memorial descritivo, com Registro de ART junto ao CREA, Honorários de responsabilidade técnica e consultoria. | C9: hectares | D9: 1 | E9: 200 | F9: =D9*E9 -> 200 | G9: RECEITA
A10: 2.0 | B10: Despachante Imobiliário
A11: 2.1 | B11: Correção/ atualização do CCIR, registro do CIB e Atualização do CAR | C11: Verba | D11: 1 | E11: 1500 | F11: =D11*E11 -> 1500
A12: ,
B14: Total | F14: =SUM(F3:F13) -> 2900 | G14: =F14-E25 -> 2215
B17: DESPESAS | C17: QUANT | D17: PREÇO | E17: VALOR
B18: ALIMENTAÇÃO | C18: 2 | D18: 75 | E18: =C18*D18 -> 150
B19: HOSPEDAGEM | C19: 0 | D19: 250 | E19: =C19*D19 -> 0
B20: COMBUSTIVEL | C20: 0.5 | D20: 170 | E20: =C20*D20 -> 85
B21: AJUDANTES | C21: 1 | D21: 150 | E21: =C21*D21 -> 150
B22: PLAQUETAS | C22: 5 | D22: 30 | E22: =C22*D22 -> 150
B23: PROCESSAMENTO DOS DADOS | C23: 1 | D23: 150 | E23: =C23*D23 -> 150
E25: =SUM(E18:E24) -> 685

Sheet SIÂ-TIO BELEM
A1: ITENS | B1: DESCRIÇÃO | C1: UND | D1: QUANT. | E1: PREÇO | F1: VALOR
E2: UNITÁRIIO | F2: VALOR
A3: 1.0 | B3: Mobilização
A4: 1.1 | B4: Logistica e Mobilização de equipamentos e pessoas para realização do levantamento para adquação do levantamento para atender as especificações do Manual de Georreferenciamento (MTGIR, 2022) | C4: VERBA | D4: 1 | E4: 450 | F4: =D4*E4 -> 450
A5: 2.0 | B5: Levantamento Cadastral Territorial (campo e Escritòrio)
A6: 2.3 | B6: Confecção e Implantação de Marcos e plaquetas Padrão INCRA. | C6: UNID | D6: 2 | E6: 75 | F6: =D6*E6 -> 150
A7: 2.2 | B7: Serviços de campo para medição e Georreferenciamento dos vértices definidores do perímetro total conforme estabelece o Manual Técnico de Georrferenciamendo Imóveis Rurais 2022. | C7: hectares | D7: 14 | E7: 25 | F7: =D7*E7 -> 350
A8: 2.4 | B8: Serviços de Gabinete: processamento e analise de dados, elaboração de planilhas eletrônicas, relatórios, cálculos e Geração de Planilhas ODS para Certificação | C8: verba | D8: 1 | E8: 250 | F8: =D8*E8 -> 250
A9: 2.6 | B9: Elaboração de planta em CAD e calculos necessários com impressão em formato ABNT em 3 vias com a elaboração do memorial descritivo, com Registro de ART junto ao CREA, Honorários de responsabilidade técnica e consultoria. | C9: hectares | D9: 1 | E9: 200 | F9: =D9*E9 -> 200 | G9: RECEITA
A10: 2.0 | B10: Despachante Imobiliário
A11: 2.1 | B11: Correção/ atualização do CCIR, registro do CIB e Atualização do CAR | C11: Verba | D11: 1 | E11: 1500 | F11: =D11*E11 -> 1500
A12: ,
B14: Total | F14: =SUM(F3:F13) -> 2900 | G14: =F14-E25 -> 2215
B17: DESPESAS | C17: QUANT | D17: PREÇO | E17: VALOR
B18: ALIMENTAÇÃO | C18: 2 | D18: 75 | E18: =C18*D18 -> 150
B19: HOSPEDAGEM | C19: 0 | D19: 250 | E19: =C19*D19 -> 0
B20: COMBUSTIVEL | C20: 0.5 | D20: 170 | E20: =C20*D20 -> 85
B21: AJUDANTES | C21: 1 | D21: 150 | E21: =C21*D21 -> 150
B22: PLAQUETAS | C22: 5 | D22: 30 | E22: =C22*D22 -> 150
B23: PROCESSAMENTO DOS DADOS | C23: 1 | D23: 150 | E23: =C23*D23 -> 150
E25: =SUM(E18:E24) -> 685

Sheet GRANJA PALACETE
A1: ITENS | B1: DESCRIÇÃO | C1: UND | D1: QUANT. | E1: PREÇO | F1: VALOR
E2: UNITÁRIIO | F2: VALOR
A3: 1.0 | B3: Mobilização
A4: 1.1 | B4: Logistica e Mobilização de equipamentos e pessoas para realização do levantamento para adquação do levantamento para atender as especificações do Manual de Georreferenciamento (MTGIR, 2022) | C4: VERBA | D4: 1 | E4: 450 | F4: =D4*E4 -> 450
A5: 2.0 | B5: Levantamento Cadastral Territorial (campo e Escritòrio)
A6: 2.3 | B6: Confecção e Implantação de Marcos e plaquetas Padrão INCRA. | C6: UNID | D6: 2 | E6: 75 | F6: =D6*E6 -> 150
A7: 2.2 | B7: Serviços de campo para medição e Georreferenciamento dos vértices definidores do perímetro total conforme estabelece o Manual Técnico de Georrferenciamendo Imóveis Rurais 2022. | C7: hectares | D7: 14 | E7: 25 | F7: =D7*E7 -> 350
A8: 2.4 | B8: Serviços de Gabinete: processamento e analise de dados, elaboração de planilhas eletrônicas, relatórios, cálculos e Geração de Planilhas ODS para Certificação | C8: verba | D8: 1 | E8: 250 | F8: =D8*E8 -> 250
A9: 2.6 | B9: Elaboração de planta em CAD e calculos necessários com impressão em formato ABNT em 3 vias com a elaboração do memorial descritivo, com Registro de ART junto ao CREA, Honorários de responsabilidade técnica e consultoria. | C9: hectares | D9: 1 | E9: 200 | F9: =D9*E9 -> 200 | G9: RECEITA
A10: 2.0 | B10: Despachante Imobiliário
A11: 2.1 | B11: Correção/ atualização do CCIR, registro do CIB e Atualização do CAR | C11: Verba | D11: 1 | E11: 1500 | F11: =D11*E11 -> 1500
A12: ,
B14: Total | F14: =SUM(F3:F13) -> 2900 | G14: =F14-E25 -> 2215
B17: DESPESAS | C17: QUANT | D17: PREÇO | E17: VALOR
B18: ALIMENTAÇÃO | C18: 2 | D18: 75 | E18: =C18*D18 -> 150
B19: HOSPEDAGEM | C19: 0 | D19: 250 | E19: =C19*D19 -> 0
B20: COMBUSTIVEL | C20: 0.5 | D20: 170 | E20: =C20*D20 -> 85
B21: AJUDANTES | C21: 1 | D21: 150 | E21: =C21*D21 -> 150
B22: PLAQUETAS | C22: 5 | D22: 30 | E22: =C22*D22 -> 150
B23: PROCESSAMENTO DOS DADOS | C23: 1 | D23: 150 | E23: =C23*D23 -> 150
E25: =SUM(E18:E24) -> 685

Sheet GRANJA GRANJITA
A1: ITENS | B1: DESCRIÇÃO | C1: UND | D1: QUANT. | E1: PREÇO | F1: VALOR
E2: UNITÁRIIO | F2: VALOR
A3: 1.0 | B3: Mobilização
A4: 1.1 | B4: Logistica e Mobilização de equipamentos e pessoas para realização do levantamento para adquação do levantamento para atender as especificações do Manual de Georreferenciamento (MTGIR, 2022) | C4: VERBA | D4: 1 | E4: 450 | F4: =D4*E4 -> 450
A5: 2.0 | B5: Levantamento Cadastral Territorial (campo e Escritòrio)
A6: 2.3 | B6: Confecção e Implantação de Marcos e plaquetas Padrão INCRA. | C6: UNID | D6: 2 | E6: 75 | F6: =D6*E6 -> 150
A7: 2.2 | B7: Serviços de campo para medição e Georreferenciamento dos vértices definidores do perímetro total conforme estabelece o Manual Técnico de Georrferenciamendo Imóveis Rurais 2022. | C7: hectares | D7: 58 | E7: 25 | F7: =D7*E7 -> 1450
A8: 2.4 | B8: Serviços de Gabinete: processamento e analise de dados, elaboração de planilhas eletrônicas, relatórios, cálculos e Geração de Planilhas ODS para Certificação | C8: verba | D8: 1 | E8: 250 | F8: =D8*E8 -> 250
A9: 2.6 | B9: Elaboração de planta em CAD e calculos necessários com impressão em formato ABNT em 3 vias com a elaboração do memorial descritivo, com Registro de ART junto ao CREA, Honorários de responsabilidade técnica e consultoria. | C9: hectares | D9: 1 | E9: 200 | F9: =D9*E9 -> 200 | G9: RECEITA
A10: 2.0 | B10: Despachante Imobiliário
A11: 2.1 | B11: Correção/ atualização do CCIR, registro do CIB e Atualização do CAR | C11: Verba | D11: 1 | E11: 1500 | F11: =D11*E11 -> 1500
A12: ,
F13: =SUM(F3:F12) -> 4000
B14: Total | F14: =SUM(F4:F9) -> 2500 | G14: =F14-E25 -> 1785
B17: DESPESAS | C17: QUANT | D17: PREÇO | E17: VALOR
B18: ALIMENTAÇÃO | C18: 2 | D18: 75 | E18: =C18*D18 -> 150
B19: HOSPEDAGEM | C19: 0 | D19: 250 | E19: =C19*D19 -> 0
B20: COMBUSTIVEL | C20: 0.5 | D20: 170 | E20: =C20*D20 -> 85
B21: AJUDANTES | C21: 1 | D21: 180 | E21: =C21*D21 -> 180
B22: PLAQUETAS | C22: 5 | D22: 30 | E22: =C22*D22 -> 150
B23: PROCESSAMENTO DOS DADOS | C23: 1 | D23: 150 | E23: =C23*D23 -> 150
E25: =SUM(E18:E24) -> 715

Sheet GRANJA SÃO LUIS
A1: ITENS | B1: DESCRIÇÃO | C1: UND | D1: QUANT. | E1: PREÇO | F1: VALOR
E2: UNITÁRIIO | F2: VALOR
A3: 1.0 | B3: Mobilização
A4: 1.1 | B4: Logistica e Mobilização de equipamentos e pessoas para realização do levantamento para adquação do levantamento para atender as especificações do Manual de Georreferenciamento (MTGIR, 2022) | C4: VERBA | D4: 1 | E4: 450 | F4: =D4*E4 -> 450
A5: 2.0 | B5: Levantamento Cadastral Territorial (campo e Escritòrio)
A6: 2.3 | B6: Confecção e Implantação de Marcos e plaquetas Padrão INCRA. | C6: UNID | D6: 2 | E6: 75 | F6: =D6*E6 -> 150
A7: 2.2 | B7: Serviços de campo para medição e Georreferenciamento dos vértices definidores do perímetro total conforme estabelece o Manual Técnico de Georrferenciamendo Imóveis Rurais 2022. | C7: hectares | D7: 28.9 | E7: 25 | F7: =D7*E7 -> 722.5
A8: 2.4 | B8: Serviços de Gabinete: processamento e analise de dados, elaboração de planilhas eletrônicas, relatórios, cálculos e Geração de Planilhas ODS para Certificação | C8: verba | D8: 1 | E8: 250 | F8: =D8*E8 -> 250
A9: 2.6 | B9: Elaboração de planta em CAD e calculos necessários com impressão em formato ABNT em 3 vias com a elaboração do memorial descritivo, com Registro de ART junto ao CREA, Honorários de responsabilidade técnica e consultoria. | C9: hectares | D9: 1 | E9: 200 | F9: =D9*E9 -> 200 | G9: RECEITA
A10: 2.0 | B10: Despachante Imobiliário
A11: 2.1 | B11: Correção/ atualização do CCIR, registro do CIB e Atualização do CAR | C11: Verba | D11: 1 | E11: 1500 | F11: =D11*E11 -> 1500
A12: ,
B14: Total | F14: =SUM(F3:F13) -> 3272.5 | G14: =F14-E25 -> 2557.5
B17: DESPESAS | C17: QUANT | D17: PREÇO | E17: VALOR
B18: ALIMENTAÇÃO | C18: 2 | D18: 75 | E18: =C18*D18 -> 150
B19: HOSPEDAGEM | C19: 0 | D19: 250 | E19: =C19*D19 -> 0
B20: COMBUSTIVEL | C20: 0.5 | D20: 170 | E20: =C20*D20 -> 85
B21: AJUDANTES | C21: 1 | D21: 180 | E21: =C21*D21 -> 180
B22: PLAQUETAS | C22: 5 | D22: 30 | E22: =C22*D22 -> 150
B23: PROCESSAMENTO DOS DADOS | C23: 1 | D23: 150 | E23: =C23*D23 -> 150
E25: =SUM(E18:E24) -> 715

Sheet GRANJA SANTA ELIZIA I
A1: ITENS | B1: DESCRIÇÃO | C1: UND | D1: QUANT. | E1: PREÇO | F1: VALOR
E2: UNITÁRIIO | F2: VALOR
A3: 1.0 | B3: Mobilização
A4: 1.1 | B4: Logistica e Mobilização de equipamentos e pessoas para realização do levantamento para adquação do levantamento para atender as especificações do Manual de Georreferenciamento (MTGIR, 2022) | C4: VERBA | D4: 1 | E4: 450 | F4: =D4*E4 -> 450
A5: 2.0 | B5: Levantamento Cadastral Territorial (campo e Escritòrio)
A6: 2.3 | B6: Confecção e Implantação de Marcos e plaquetas Padrão INCRA. | C6: UNID | D6: 2 | E6: 75 | F6: =D6*E6 -> 150
A7: 2.2 | B7: Serviços de campo para medição e Georreferenciamento dos vértices definidores do perímetro total conforme estabelece o Manual Técnico de Georrferenciamendo Imóveis Rurais 2022. | C7: hectares | D7: 13.9 | E7: 25 | F7: =D7*E7 -> 347.5
A8: 2.4 | B8: Serviços de Gabinete: processamento e analise de dados, elaboração de planilhas eletrônicas, relatórios, cálculos e Geração de Planilhas ODS para Certificação | C8: verba | D8: 1 | E8: 250 | F8: =D8*E8 -> 250
A9: 2.6 | B9: Elaboração de planta em CAD e calculos necessários com impressão em formato ABNT em 3 vias com a elaboração do memorial descritivo, com Registro de ART junto ao CREA, Honorários de responsabilidade técnica e consultoria. | C9: hectares | D9: 1 | E9: 200 | F9: =D9*E9 -> 200 | G9: RECEITA
A10: 2.0 | B10: Despachante Imobiliário
A11: 2.1 | B11: Correção/ atualização do CCIR, registro do CIB e Atualização do CAR | C11: Verba | D11: 1 | E11: 1500 | F11: =D11*E11 -> 1500
A12: ,
F13: =SUM(F3:F12) -> 2897.5
B14: Total | F14: =SUM(F4:F9) -> 1397.5 | G14: =F14-E25 -> 732.5
B17: DESPESAS | C17: QUANT | D17: PREÇO | E17: VALOR
B18: ALIMENTAÇÃO | C18: 2 | D18: 50 | E18: =C18*D18 -> 100
B19: HOSPEDAGEM | C19: 0 | D19: 250 | E19: =C19*D19 -> 0
B20: COMBUSTIVEL | C20: 0.5 | D20: 170 | E20: =C20*D20 -> 85
B21: AJUDANTES | C21: 1 | D21: 180 | E21: =C21*D21 -> 180
B22: PLAQUETAS | C22: 5 | D22: 30 | E22: =C22*D22 -> 150
B23: PROCESSAMENTO DOS DADOS | C23: 1 | D23: 150 | E23: =C23*D23 -> 150
E25: =SUM(E18:E24) -> 665

Sheet FAZENDA VARZEA VERDE II
A1: ITENS | B1: DESCRIÇÃO | C1: UND | D1: QUANT. | E1: PREÇO | F1: VALOR
E2: UNITÁRIIO | F2: VALOR
A3: 1.0 | B3: Mobilização
A4: 1.1 | B4: Logistica e Mobilização de equipamentos e pessoas para realização do levantamento para adquação do levantamento para atender as especificações do Manual de Georreferenciamento (MTGIR, 2022) | C4: VERBA | D4: 1 | E4: 1500 | F4: =D4*E4 -> 1500
A5: 2.0 | B5: Levantamento Cadastral Territorial (campo e Escritòrio)
A6: 2.3 | B6: Confecção e Implantação de Marcos e plaquetas Padrão INCRA. | C6: UNID | D6: 2 | E6: 75 | F6: =D6*E6 -> 150
A7: 2.2 | B7: Serviços de campo para medição e Georreferenciamento dos vértices definidores do perímetro total conforme estabelece o Manual Técnico de Georrferenciamendo Imóveis Rurais 2022. | C7: hectares | D7: 31.1 | E7: 50 | F7: =D7*E7 -> 1555
A8: 2.4 | B8: Serviços de Gabinete: processamento e analise de dados, elaboração de planilhas eletrônicas, relatórios, cálculos e Geração de Planilhas ODS para Certificação | C8: verba | D8: 1 | E8: 250 | F8: =D8*E8 -> 250
A9: 2.6 | B9: Elaboração de planta em CAD e calculos necessários com impressão em formato ABNT em 3 vias com a elaboração do memorial descritivo, com Registro de ART junto ao CREA, Honorários de responsabilidade técnica e consultoria. | C9: hectares | D9: 1 | E9: 200 | F9: =D9*E9 -> 200 | G9: RECEITA
A10: 2.0 | B10: Despachante Imobiliário
A11: 2.1 | B11: Correção/ atualização do CCIR, registro do CIB e Atualização do CAR | C11: Verba | D11: 1 | E11: 1500 | F11: =D11*E11 -> 1500
A12: ,
B14: Total | F14: =SUM(F3:F13) -> 5155 | G14: =F14-E25 -> 3640
B17: DESPESAS | C17: QUANT | D17: PREÇO | E17: VALOR
B18: ALIMENTAÇÃO | C18: 2 | D18: 200 | E18: =C18*D18 -> 400
B19: HOSPEDAGEM | C19: 2 | D19: 250 | E19: =C19*D19 -> 500
B20: COMBUSTIVEL | C20: 0.5 | D20: 170 | E20: =C20*D20 -> 85
B21: AJUDANTES | C21: 1 | D21: 180 | E21: =C21*D21 -> 180
B22: PLAQUETAS | C22: 5 | D22: 30 | E22: =C22*D22 -> 150
B23: PROCESSAMENTO DOS DADOS | C23: 1 | D23: 200 | E23: =C23*D23 -> 200
E25: =SUM(E18:E24) -> 1515

Sheet GRANJA PITANGA
A1: ITENS | B1: DESCRIÇÃO | C1: UND | D1: QUANT. | E1: PREÇO | F1: VALOR
E2: UNITÁRIIO | F2: VALOR
A3: 1.0 | B3: Mobilização
A4: 1.1 | B4: Logistica e Mobilização de equipamentos e pessoas para realização do levantamento para adquação do levantamento para atender as especificações do Manual de Georreferenciamento (MTGIR, 2022) | C4: VERBA | D4: 1 | E4: 1500 | F4: =D4*E4 -> 1500
A5: 2.0 | B5: Levantamento Cadastral Territorial (campo e Escritòrio)
A6: 2.3 | B6: Confecção e Implantação de Marcos e plaquetas Padrão INCRA. | C6: UNID | D6: 2 | E6: 75 | F6: =D6*E6 -> 150
A7: 2.2 | B7: Serviços de campo para medição e Georreferenciamento dos vértices definidores do perímetro total conforme estabelece o Manual Técnico de Georrferenciamendo Imóveis Rurais 2022. | C7: hectares | D7: 31.1 | E7: 50 | F7: =D7*E7 -> 1555
A8: 2.4 | B8: Serviços de Gabinete: processamento e analise de dados, elaboração de planilhas eletrônicas, relatórios, cálculos e Geração de Planilhas ODS para Certificação | C8: verba | D8: 1 | E8: 250 | F8: =D8*E8 -> 250
A9: 2.6 | B9: Elaboração de planta em CAD e calculos necessários com impressão em formato ABNT em 3 vias com a elaboração do memorial descritivo, com Registro de ART junto ao CREA, Honorários de responsabilidade técnica e consultoria. | C9: hectares | D9: 1 | E9: 200 | F9: =D9*E9 -> 200 | G9: RECEITA
A10: 2.0 | B10: Despachante Imobiliário
A11: 2.1 | B11: Correção/ atualização do CCIR, registro do CIB e Atualização do CAR | C11: Verba | D11: 1 | E11: 1500 | F11: =D11*E11 -> 1500
A12: ,
B14: Total | F14: =SUM(F3:F13) -> 5155 | G14: =F14-E25 -> 2928
B17: DESPESAS | C17: QUANT | D17: PREÇO | E17: VALOR
B18: ALIMENTAÇÃO | C18: 2 | D18: 200 | E18: =C18*D18 -> 400
B19: HOSPEDAGEM | C19: 2 | D19: 250 | E19: =C19*D19 -> 500
B20: COMBUSTIVEL | C20: 1 | D20: 797 | E20: =C20*D20 -> 797
B21: AJUDANTES | C21: 1 | D21: 180 | E21: =C21*D21 -> 180
B22: PLAQUETAS | C22: 5 | D22: 30 | E22: =C22*D22 -> 150
B23: PROCESSAMENTO DOS DADOS | C23: 1 | D23: 200 | E23: =C23*D23 -> 200
E25: =SUM(E18:E24) -> 2227

Sheet FAZENDA NOSSA SENHORA DE FATIMA
A1: ITENS | B1: DESCRIÇÃO | C1: UND | D1: QUANT. | E1: PREÇO | F1: VALOR
E2: UNITÁRIIO | F2: VALOR
A3: 1.0 | B3: Mobilização
A4: 1.1 | B4: Logistica e Mobilização de equipamentos e pessoas para realização do levantamento para adquação do levantamento para atender as especificações do Manual de Georreferenciamento (MTGIR, 2022) | C4: VERBA | D4: 1 | E4: 1500 | F4: =D4*E4 -> 1500
A5: 2.0 | B5: Levantamento Cadastral Territorial (campo e Escritòrio)
A6: 2.3 | B6: Confecção e Implantação de Marcos e plaquetas Padrão INCRA. | C6: UNID | D6: 2 | E6: 75 | F6: =D6*E6 -> 150
A7: 2.2 | B7: Serviços de campo para medição e Georreferenciamento dos vértices definidores do perímetro total conforme estabelece o Manual Técnico de Georrferenciamendo Imóveis Rurais 2022. | C7: hectares | D7: 31.1 | E7: 50 | F7: =D7*E7 -> 1555
A8: 2.4 | B8: Serviços de Gabinete: processamento e analise de dados, elaboração de planilhas eletrônicas, relatórios, cálculos e Geração de Planilhas ODS para Certificação | C8: verba | D8: 1 | E8: 250 | F8: =D8*E8 -> 250
A9: 2.6 | B9: Elaboração de planta em CAD e calculos necessários com impressão em formato ABNT em 3 vias com a elaboração do memorial descritivo, com Registro de ART junto ao CREA, Honorários de responsabilidade técnica e consultoria. | C9: hectares | D9: 1 | E9: 200 | F9: =D9*E9 -> 200 | G9: RECEITA
A10: 2.0 | B10: Despachante Imobiliário
A11: 2.1 | B11: Correção/ atualização do CCIR, registro do CIB e Atualização do CAR | C11: Verba | D11: 1 | E11: 1500 | F11: =D11*E11 -> 1500
A12: ,
B14: Total | F14: =SUM(F3:F13) -> 5155 | G14: =F14-E25 -> 2928
B17: DESPESAS | C17: QUANT | D17: PREÇO | E17: VALOR
B18: ALIMENTAÇÃO | C18: 2 | D18: 200 | E18: =C18*D18 -> 400
B19: HOSPEDAGEM | C19: 2 | D19: 250 | E19: =C19*D19 -> 500
B20: COMBUSTIVEL+DEPRECIAÇÃO DO VEICULO | C20: 1 | D20: 797 | E20: =C20*D20 -> 797
B21: AJUDANTES | C21: 1 | D21: 180 | E21: =C21*D21 -> 180
B22: PLAQUETAS | C22: 5 | D22: 30 | E22: =C22*D22 -> 150
B23: PROCESSAMENTO DOS DADOS | C23: 1 | D23: 200 | E23: =C23*D23 -> 200
E25: =SUM(E18:E24) -> 2227

Sheet GRANJA HORTA VELHA
A1: ITENS | B1: DESCRIÇÃO | C1: UND | D1: QUANT. | E1: PREÇO | F1: VALOR
E2: UNITÁRIIO | F2: VALOR
A3: 1.0 | B3: Mobilização
A4: 1.1 | B4: Logistica e Mobilização de equipamentos e pessoas para realização do levantamento para adquação do levantamento para atender as especificações do Manual de Georreferenciamento (MTGIR, 2022) | C4: VERBA | D4: 1 | E4: 1500 | F4: =D4*E4 -> 1500
A5: 2.0 | B5: Levantamento Cadastral Territorial (campo e Escritòrio)
A6: 2.3 | B6: Confecção e Implantação de Marcos e plaquetas Padrão INCRA. | C6: UNID | D6: 2 | E6: 75 | F6: =D6*E6 -> 150
A7: 2.2 | B7: Serviços de campo para medição e Georreferenciamento dos vértices definidores do perímetro total conforme estabelece o Manual Técnico de Georrferenciamendo Imóveis Rurais 2022. | C7: hectares | D7: 20.2 | E7: 50 | F7: =D7*E7 -> 1010
A8: 2.4 | B8: Serviços de Gabinete: processamento e analise de dados, elaboração de planilhas eletrônicas, relatórios, cálculos e Geração de Planilhas ODS para Certificação | C8: verba | D8: 1 | E8: 250 | F8: =D8*E8 -> 250
A9: 2.6 | B9: Elaboração de planta em CAD e calculos necessários com impressão em formato ABNT em 3 vias com a elaboração do memorial descritivo, com Registro de ART junto ao CREA, Honorários de responsabilidade técnica e consultoria. | C9: hectares | D9: 1 | E9: 200 | F9: =D9*E9 -> 200 | G9: RECEITA
A10: 2.0 | B10: Despachante Imobiliário
A11: 2.1 | B11: Correção/ atualização do CCIR, registro do CIB e Atualização do CAR | C11: Verba | D11: 1 | E11: 1500 | F11: =D11*E11 -> 1500
A12: ,
B14: Total | F14: =SUM(F3:F13) -> 4610 | G14: =F14-E25 -> 2383
B17: DESPESAS | C17: QUANT | D17: PREÇO | E17: VALOR
B18: ALIMENTAÇÃO | C18: 2 | D18: 200 | E18: =C18*D18 -> 400
B19: HOSPEDAGEM | C19: 2 | D19: 250 | E19: =C19*D19 -> 500
B20: COMBUSTIVEL+DEPRECIAÇÃO DO VEICULO | C20: 1 | D20: 797 | E20: =C20*D20 -> 797
B21: AJUDANTES | C21: 1 | D21: 180 | E21: =C21*D21 -> 180
B22: PLAQUETAS | C22: 5 | D22: 30 | E22: =C22*D22 -> 150
B23: PROCESSAMENTO DOS DADOS | C23: 1 | D23: 200 | E23: =C23*D23 -> 200
E25: =SUM(E18:E24) -> 2227

Sheet GRANJA SANTO ANTONIO
A1: ITENS | B1: DESCRIÇÃO | C1: UND | D1: QUANT. | E1: PREÇO | F1: VALOR
E2: UNITÁRIIO | F2: VALOR
A3: 1.0 | B3: Mobilização
A4: 1.1 | B4: Logistica e Mobilização de equipamentos e pessoas para realização do levantamento para adquação do levantamento para atender as especificações do Manual de Georreferenciamento (MTGIR, 2022) | C4: VERBA | D4: 1 | E4: 450 | F4: =D4*E4 -> 450
A5: 2.0 | B5: Levantamento Cadastral Territorial (campo e Escritòrio)
A6: 2.3 | B6: Confecção e Implantação de Marcos e plaquetas Padrão INCRA. | C6: UNID | D6: 2 | E6: 75 | F6: =D6*E6 -> 150
A7: 2.2 | B7: Serviços de campo para medição e Georreferenciamento dos vértices definidores do perímetro total conforme estabelece o Manual Técnico de Georrferenciamendo Imóveis Rurais 2022. | C7: hectares | D7: 8.8951 | E7: 25 | F7: =D7*E7 -> 222.3775
A8: 2.4 | B8: Serviços de Gabinete: processamento e analise de dados, elaboração de planilhas eletrônicas, relatórios, cálculos e Geração de Planilhas ODS para Certificação | C8: verba | D8: 1 | E8: 250 | F8: =D8*E8 -> 250
A9: 2.6 | B9: Elaboração de planta em CAD e calculos necessários com impressão em formato ABNT em 3 vias com a elaboração do memorial descritivo, com Registro de ART junto ao CREA, Honorários de responsabilidade técnica e consultoria. | C9: hectares | D9: 1 | E9: 200 | F9: =D9*E9 -> 200 | G9: RECEITA
A10: 2.0 | B10: Despachante Imobiliário
A11: 2.1 | B11: Correção/ atualização do CCIR, registro do CIB e Atualização do CAR | C11: Verba | D11: 1 | E11: 1500 | F11: =D11*E11 -> 1500
A12: ,
B14: Total | F14: =SUM(F3:F13) -> 2772.3775 | G14: =F14-E25 -> 2057.3775
B17: DESPESAS | C17: QUANT | D17: PREÇO | E17: VALOR
B18: ALIMENTAÇÃO | C18: 2 | D18: 75 | E18: =C18*D18 -> 150
B19: HOSPEDAGEM | C19: 0 | D19: 250 | E19: =C19*D19 -> 0
B20: COMBUSTIVEL | C20: 0.5 | D20: 170 | E20: =C20*D20 -> 85
B21: AJUDANTES | C21: 1 | D21: 180 | E21: =C21*D21 -> 180
B22: PLAQUETAS | C22: 5 | D22: 30 | E22: =C22*D22 -> 150
B23: PROCESSAMENTO DOS DADOS | C23: 1 | D23: 150 | E23: =C23*D23 -> 150
E25: =SUM(E18:E24) -> 715

Sheet GRANJA SAO JUDAS TADEU
A1: ITENS | B1: DESCRIÇÃO | C1: UND | D1: QUANT. | E1: PREÇO | F1: VALOR
E2: UNITÁRIIO | F2: VALOR
A3: 1.0 | B3: Mobilização
A4: 1.1 | B4: Logistica e Mobilização de equipamentos e pessoas para realização do levantamento para adquação do levantamento para atender as especificações do Manual de Georreferenciamento (MTGIR, 2022) | C4: VERBA | D4: 1 | E4: 450 | F4: =D4*E4 -> 450
A5: 2.0 | B5: Levantamento Cadastral Territorial (campo e Escritòrio)
A6: 2.3 | B6: Confecção e Implantação de Marcos e plaquetas Padrão INCRA. | C6: UNID | D6: 2 | E6: 75 | F6: =D6*E6 -> 150
A7: 2.2 | B7: Serviços de campo para medição e Georreferenciamento dos vértices definidores do perímetro total conforme estabelece o Manual Técnico de Georrferenciamendo Imóveis Rurais 2022. | C7: hectares | D7: 8.066 | E7: 25 | F7: =D7*E7 -> 201.65
A8: 2.4 | B8: Serviços de Gabinete: processamento e analise de dados, elaboração de planilhas eletrônicas, relatórios, cálculos e Geração de Planilhas ODS para Certificação | C8: verba | D8: 1 | E8: 250 | F8: =D8*E8 -> 250
A9: 2.6 | B9: Elaboração de planta em CAD e calculos necessários com impressão em formato ABNT em 3 vias com a elaboração do memorial descritivo, com Registro de ART junto ao CREA, Honorários de responsabilidade técnica e consultoria. | C9: hectares | D9: 1 | E9: 200 | F9: =D9*E9 -> 200 | G9: RECEITA
A10: 2.0 | B10: Despachante Imobiliário
A11: 2.1 | B11: Correção/ atualização do CCIR, registro do CIB e Atualização do CAR | C11: Verba | D11: 1 | E11: 1500 | F11: =D11*E11 -> 1500
A12: ,
B14: Total | F14: =SUM(F3:F13) -> 2751.65 | G14: =F14-E25 -> 2036.65
B17: DESPESAS | C17: QUANT | D17: PREÇO | E17: VALOR
B18: ALIMENTAÇÃO | C18: 2 | D18: 75 | E18: =C18*D18 -> 150
B19: HOSPEDAGEM | C19: 0 | D19: 250 | E19: =C19*D19 -> 0
B20: COMBUSTIVEL | C20: 0.5 | D20: 170 | E20: =C20*D20 -> 85
B21: AJUDANTES | C21: 1 | D21: 180 | E21: =C21*D21 -> 180
B22: PLAQUETAS | C22: 5 | D22: 30 | E22: =C22*D22 -> 150
B23: PROCESSAMENTO DOS DADOS | C23: 1 | D23: 150 | E23: =C23*D23 -> 150
E25: =SUM(E18:E24) -> 715

Sheet GRANJA GAVIAO
A1: ITENS | B1: DESCRIÇÃO | C1: UND | D1: QUANT. | E1: PREÇO | F1: VALOR
E2: UNITÁRIIO | F2: VALOR
A3: 1.0 | B3: Mobilização
A4: 1.1 | B4: Logistica e Mobilização de equipamentos e pessoas para realização do levantamento para adquação do levantamento para atender as especificações do Manual de Georreferenciamento (MTGIR, 2022) | C4: VERBA | D4: 1 | E4: 450 | F4: =D4*E4 -> 450
A5: 2.0 | B5: Levantamento Cadastral Territorial (campo e Escritòrio)
A6: 2.3 | B6: Confecção e Implantação de Marcos e plaquetas Padrão INCRA. | C6: UNID | D6: 2 | E6: 75 | F6: =D6*E6 -> 150
A7: 2.2 | B7: Serviços de campo para medição e Georreferenciamento dos vértices definidores do perímetro total conforme estabelece o Manual Técnico de Georrferenciamendo Imóveis Rurais 2022. | C7: hectares | D7: 8.84 | E7: 25 | F7: =D7*E7 -> 221
A8: 2.4 | B8: Serviços de Gabinete: processamento e analise de dados, elaboração de planilhas eletrônicas, relatórios, cálculos e Geração de Planilhas ODS para Certificação | C8: verba | D8: 1 | E8: 250 | F8: =D8*E8 -> 250
A9: 2.6 | B9: Elaboração de planta em CAD e calculos necessários com impressão em formato ABNT em 3 vias com a elaboração do memorial descritivo, com Registro de ART junto ao CREA, Honorários de responsabilidade técnica e consultoria. | C9: hectares | D9: 1 | E9: 200 | F9: =D9*E9 -> 200 | G9: RECEITA
A10: 2.0 | B10: Despachante Imobiliário
A11: 2.1 | B11: Correção/ atualização do CCIR, registro do CIB e Atualização do CAR | C11: Verba | D11: 1 | E11: 1500 | F11: =D11*E11 -> 1500
A12: ,
B14: Total | F14: =SUM(F3:F13) -> 2771 | G14: =F14-E25 -> 2056
B17: DESPESAS | C17: QUANT | D17: PREÇO | E17: VALOR
B18: ALIMENTAÇÃO | C18: 2 | D18: 75 | E18: =C18*D18 -> 150
B19: HOSPEDAGEM | C19: 0 | D19: 250 | E19: =C19*D19 -> 0
B20: COMBUSTIVEL | C20: 0.5 | D20: 170 | E20: =C20*D20 -> 85
B21: AJUDANTES | C21: 1 | D21: 180 | E21: =C21*D21 -> 180
B22: PLAQUETAS | C22: 5 | D22: 30 | E22: =C22*D22 -> 150
B23: PROCESSAMENTO DOS DADOS | C23: 1 | D23: 150 | E23: =C23*D23 -> 150
E25: =SUM(E18:E24) -> 715

Sheet GRANJA HERCULANO BANDEIRA PARTE
A1: ITENS | B1: DESCRIÇÃO | C1: UND | D1: QUANT. | E1: PREÇO | F1: VALOR
E2: UNITÁRIIO | F2: VALOR
A3: 1.0 | B3: Mobilização
A4: 1.1 | B4: Logistica e Mobilização de equipamentos e pessoas para realização do levantamento para adquação do levantamento para atender as especificações do Manual de Georreferenciamento (MTGIR, 2022) | C4: VERBA | D4: 1 | E4: 450 | F4: =D4*E4 -> 450
A5: 2.0 | B5: Levantamento Cadastral Territorial (campo e Escritòrio)
A6: 2.3 | B6: Confecção e Implantação de Marcos e plaquetas Padrão INCRA. | C6: UNID | D6: 2 | E6: 75 | F6: =D6*E6 -> 150
A7: 2.2 | B7: Serviços de campo para medição e Georreferenciamento dos vértices definidores do perímetro total conforme estabelece o Manual Técnico de Georrferenciamendo Imóveis Rurais 2022. | C7: hectares | D7: 5.95 | E7: 25 | F7: =D7*E7 -> 148.75
A8: 2.4 | B8: Serviços de Gabinete: processamento e analise de dados, elaboração de planilhas eletrônicas, relatórios, cálculos e Geração de Planilhas ODS para Certificação | C8: verba | D8: 1 | E8: 250 | F8: =D8*E8 -> 250
A9: 2.6 | B9: Elaboração de planta em CAD e calculos necessários com impressão em formato ABNT em 3 vias com a elaboração do memorial descritivo, com Registro de ART junto ao CREA, Honorários de responsabilidade técnica e consultoria. | C9: hectares | D9: 1 | E9: 200 | F9: =D9*E9 -> 200 | G9: RECEITA
A10: 2.0 | B10: Despachante Imobiliário
A11: 2.1 | B11: Correção/ atualização do CCIR, registro do CIB e Atualização do CAR | C11: Verba | D11: 1 | E11: 1500 | F11: =D11*E11 -> 1500
A12: ,
B14: Total | F14: =SUM(F3:F13) -> 2698.75 | G14: =F14-E25 -> 1983.75
B17: DESPESAS | C17: QUANT | D17: PREÇO | E17: VALOR
B18: ALIMENTAÇÃO | C18: 2 | D18: 75 | E18: =C18*D18 -> 150
B19: HOSPEDAGEM | C19: 0 | D19: 250 | E19: =C19*D19 -> 0
B20: COMBUSTIVEL | C20: 0.5 | D20: 170 | E20: =C20*D20 -> 85
B21: AJUDANTES | C21: 1 | D21: 180 | E21: =C21*D21 -> 180
B22: PLAQUETAS | C22: 5 | D22: 30 | E22: =C22*D22 -> 150
B23: PROCESSAMENTO DOS DADOS | C23: 1 | D23: 150 | E23: =C23*D23 -> 150
E25: =SUM(E18:E24) -> 715

Sheet GRANJA SIMMENTEL
A1: ITENS | B1: DESCRIÇÃO | C1: UND | D1: QUANT. | E1: PREÇO | F1: VALOR
E2: UNITÁRIIO | F2: VALOR
A3: 1.0 | B3: Mobilização
A4: 1.1 | B4: Logistica e Mobilização de equipamentos e pessoas para realização do levantamento para adquação do levantamento para atender as especificações do Manual de Georreferenciamento (MTGIR, 2022) | C4: VERBA | D4: 1 | E4: 450 | F4: =D4*E4 -> 450
A5: 2.0 | B5: Levantamento Cadastral Territorial (campo e Escritòrio)
A6: 2.3 | B6: Confecção e Implantação de Marcos e plaquetas Padrão INCRA. | C6: UNID | D6: 2 | E6: 75 | F6: =D6*E6 -> 150
A7: 2.2 | B7: Serviços de campo para medição e Georreferenciamento dos vértices definidores do perímetro total conforme estabelece o Manual Técnico de Georrferenciamendo Imóveis Rurais 2022. | C7: hectares | D7: 10 | E7: 25 | F7: =D7*E7 -> 250
A8: 2.4 | B8: Serviços de Gabinete: processamento e analise de dados, elaboração de planilhas eletrônicas, relatórios, cálculos e Geração de Planilhas ODS para Certificação | C8: verba | D8: 1 | E8: 250 | F8: =D8*E8 -> 250
A9: 2.6 | B9: Elaboração de planta em CAD e calculos necessários com impressão em formato ABNT em 3 vias com a elaboração do memorial descritivo, com Registro de ART junto ao CREA, Honorários de responsabilidade técnica e consultoria. | C9: hectares | D9: 1 | E9: 200 | F9: =D9*E9 -> 200 | G9: RECEITA
A10: 2.0 | B10: Despachante Imobiliário
A11: 2.1 | B11: Correção/ atualização do CCIR, registro do CIB e Atualização do CAR | C11: Verba | D11: 1 | E11: 1500 | F11: =D11*E11 -> 1500
A12: ,
B14: Total | F14: =SUM(F3:F13) -> 2800 | G14: =F14-E25 -> 2085
B17: DESPESAS | C17: QUANT | D17: PREÇO | E17: VALOR
B18: ALIMENTAÇÃO | C18: 2 | D18: 75 | E18: =C18*D18 -> 150
B19: HOSPEDAGEM | C19: 0 | D19: 250 | E19: =C19*D19 -> 0
B20: COMBUSTIVEL | C20: 0.5 | D20: 170 | E20: =C20*D20 -> 85
B21: AJUDANTES | C21: 1 | D21: 180 | E21: =C21*D21 -> 180
B22: PLAQUETAS | C22: 5 | D22: 30 | E22: =C22*D22 -> 150
B23: PROCESSAMENTO DOS DADOS | C23: 1 | D23: 150 | E23: =C23*D23 -> 150
E25: =SUM(E18:E24) -> 715
