Workbook

Sheet Painel Inicial
B3: Bem-vindo à Planilha de Viabilidade Econômica do Sienge Esse modelo de Planilha de Viabilidade Econômica permite inserir até 100 informações diferentes em cada uma das abas de Previsões Financeiras (Investimentos, Receitas, Gastos e Depreciação). Na aba Indicadores você conseguirá ver, de maneira clara, o Fluxo de Caixa e os principais Indicadores de Viabilidade do seu projeto. Acesse um dos botões do menu abaixo: | O3: Apareceu uma barra rosa no topo do arquivo dizendo que a planilha não é segura? Basta clicar em "Obter mais detalhes" e posteriormente clicar no botão “Editar mesmo assim”.
B6: Caso você precise fazer algum tipo de edição, fique tranquilo, pois esse arquivo é desbloqueado e permite a adaptação para sua empresa. E não esqueça, se as planilhas não permitirem mais o desempenho desejado para sua empresa e você quiser uma gestão mais madura, sem retrabalho e que permita fácil acesso a informações gerenciais, você precisa de um ERP, um Software de Gestão de Obras. Quem sabe não é a hora de conhecer o Sienge? Acesse: www.sienge.com.br .
B18: Faça a gestão completa de sua obra com o Sienge, saiba mais em www.sienge.com.br ou (48) 3027 8110.

Sheet Como Utilizar
B3: Como Utilizar
N5: Em todas as abas da Planilha de Viabilidade Econômica, preencha apenas os campos com fundo verde claro. Todos as outras informações são geradas automaticamente.

Sheet Taxas
A4: Taxas
G5: Em todas as abas da Planilha de Viabilidade Econômica, preencha apenas os campos com fundo verde claro. Todos as outras informações são geradas automaticamente.
A6: PIS/COFINS/ISS | B6: 0.1015
A7: IR (Imposto de Renda) | B7: 0.32
A8: TMA | B8: 0.14
A9: CDI ano (Taxa de Desconto) | B9: 0.094 | C9: Últimos 12 meses (jan-17 a jan-18)

Sheet Investimentos
A2: DESCRIÇÃO DO INVESTIMENTO | B2: Total | C2: % Total | D2: Mês 1 | E2: Mês 2 | F2: Mês 3 | G2: Mês 4 | H2: Mês 5 | I2: Mês 6 | J2: Mês 7 | K2: Mês 8 | L2: Mês 9 | M2: Mês 10 | N2: Mês 11 | O2: Mês 12 | P2: Mês 13 | Q2: Mês 14 | R2: Mês 15 | S2: Mês 16 | T2: Mês 17 | U2: Mês 18 | V2: Mês 19 | W2: Mês 20 | X2: Mês 21 | Y2: Mês 22 | Z2: Mês 23 | AA2: Mês 24 | AB2: Mês 25 | AC2: Mês 26 | AD2: Mês 27 | AE2: Mês 28 | AF2: Mês 29 | AG2: Mês 30 | AH2: Mês 31 | AI2: Mês 32 | AJ2: Mês 33 | AK2: Mês 34 | AL2: Mês 35 | AM2: Mês 36 | AN2: Mês 37 | AO2: Mês 38 | AP2: Mês 39 | AQ2: Mês 40 | AR2: Mês 41 | AS2: Mês 42 | AT2: Mês 43 | AU2: Mês 44 | AV2: Mês 45 | AW2: Mês 46 | AX2: Mês 47 | AY2: Mês 48 | AZ2: Mês 49 | BA2: Mês 50 | BB2: Mês 51 | BC2: Mês 52 | BD2: Mês 53 | BE2: Mês 54 | BF2: Mês 55 | BG2: Mês 56 | BH2: Mês 57 | BI2: Mês 58 | BJ2: Mês 59 | BK2: Mês 60
A3: Investimento Inicial | B3: 0 | C3: =B3/SUM($B$3:$B$103) -> #DIV/0! | D3: - | E3: - | F3: - | G3: - | H3: - | I3: - | J3: - | K3: - | L3: - | M3: - | N3: - | O3: - | P3: - | Q3: - | R3: - | S3: - | T3: - | U3: - | V3: - | W3: - | X3: - | Y3: - | Z3: - | AA3: - | AB3: - | AC3: - | AD3: - | AE3: - | AF3: - | AG3: - | AH3: - | AI3: - | AJ3: - | AK3: - | AL3: - | AM3: - | AN3: - | AO3: - | AP3: - | AQ3: - | AR3: - | AS3: - | AT3: - | AU3: - | AV3: - | AW3: - | AX3: - | AY3: - | AZ3: - | BA3: - | BB3: - | BC3: - | BD3: - | BE3: - | BF3: - | BG3: - | BH3: - | BI3: - | BJ3: - | BK3: -
B4: =SUM(D4:BK4) -> 0 | C4: =B4/SUM($B$3:$B$103) -> #DIV/0!
B5: =SUM(D5:BK5) -> 0 | C5: =B5/SUM($B$3:$B$103) -> #DIV/0!
B6: =SUM(D6:BK6) -> 0 | C6: =B6/SUM($B$3:$B$103) -> #DIV/0!
B7: =SUM(D7:BK7) -> 0 | C7: =B7/SUM($B$3:$B$103) -> #DIV/0!
B8: =SUM(D8:BK8) -> 0 | C8: =B8/SUM($B$3:$B$103) -> #DIV/0!
B9: =SUM(D9:BK9) -> 0 | C9: =B9/SUM($B$3:$B$103) -> #DIV/0!
B10: =SUM(D10:BK10) -> 0 | C10: =B10/SUM($B$3:$B$103) -> #DIV/0!
B11: =SUM(D11:BK11) -> 0 | C11: =B11/SUM($B$3:$B$103) -> #DIV/0!
B12: =SUM(D12:BK12) -> 0 | C12: =B12/SUM($B$3:$B$103) -> #DIV/0!
B13: =SUM(D13:BK13) -> 0 | C13: =B13/SUM($B$3:$B$103) -> #DIV/0!
B14: =SUM(D14:BK14) -> 0 | C14: =B14/SUM($B$3:$B$103) -> #DIV/0!
B15: =SUM(D15:BK15) -> 0 | C15: =B15/SUM($B$3:$B$103) -> #DIV/0!
... B103: =SUM(D103:BK103) -> 0 | C103: =B103/SUM($B$3:$B$103) -> #DIV/0!

Sheet Receitas
A2: DESCRIÇÃO DAS RECEITAS | B2: Total | C2: % Total | D2: Mês 1 | E2: Mês 2 | F2: Mês 3 | G2: Mês 4 | H2: Mês 5 | I2: Mês 6 | J2: Mês 7 | K2: Mês 8 | L2: Mês 9 | M2: Mês 10 | N2: Mês 11 | O2: Mês 12 | P2: Mês 13 | Q2: Mês 14 | R2: Mês 15 | S2: Mês 16 | T2: Mês 17 | U2: Mês 18 | V2: Mês 19 | W2: Mês 20 | X2: Mês 21 | Y2: Mês 22 | Z2: Mês 23 | AA2: Mês 24 | AB2: Mês 25 | AC2: Mês 26 | AD2: Mês 27 | AE2: Mês 28 | AF2: Mês 29 | AG2: Mês 30 | AH2: Mês 31 | AI2: Mês 32 | AJ2: Mês 33 | AK2: Mês 34 | AL2: Mês 35 | AM2: Mês 36 | AN2: Mês 37 | AO2: Mês 38 | AP2: Mês 39 | AQ2: Mês 40 | AR2: Mês 41 | AS2: Mês 42 | AT2: Mês 43 | AU2: Mês 44 | AV2: Mês 45 | AW2: Mês 46 | AX2: Mês 47 | AY2: Mês 48 | AZ2: Mês 49 | BA2: Mês 50 | BB2: Mês 51 | BC2: Mês 52 | BD2: Mês 53 | BE2: Mês 54 | BF2: Mês 55 | BG2: Mês 56 | BH2: Mês 57 | BI2: Mês 58 | BJ2: Mês 59 | BK2: Mês 60
B3: =SUM(D3:BK3) -> 0 | C3: =B3/SUM($B$3:$B$103) -> #DIV/0!
B4: =SUM(D4:BK4) -> 0 | C4: =B4/SUM($B$3:$B$103) -> #DIV/0!
B5: =SUM(D5:BK5) -> 0 | C5: =B5/SUM($B$3:$B$103) -> #DIV/0!
B6: =SUM(D6:BK6) -> 0 | C6: =B6/SUM($B$3:$B$103) -> #DIV/0!
B7: =SUM(D7:BK7) -> 0 | C7: =B7/SUM($B$3:$B$103) -> #DIV/0!
B8: =SUM(D8:BK8) -> 0 | C8: =B8/SUM($B$3:$B$103) -> #DIV/0!
B9: =SUM(D9:BK9) -> 0 | C9: =B9/SUM($B$3:$B$103) -> #DIV/0!
B10: =SUM(D10:BK10) -> 0 | C10: =B10/SUM($B$3:$B$103) -> #DIV/0!
B11: =SUM(D11:BK11) -> 0 | C11: =B11/SUM($B$3:$B$103) -> #DIV/0!
B12: =SUM(D12:BK12) -> 0 | C12: =B12/SUM($B$3:$B$103) -> #DIV/0!
B13: =SUM(D13:BK13) -> 0 | C13: =B13/SUM($B$3:$B$103) -> #DIV/0!
B14: =SUM(D14:BK14) -> 0 | C14: =B14/SUM($B$3:$B$103) -> #DIV/0!
... B103: =SUM(D103:BK103) -> 0 | C103: =B103/SUM($B$3:$B$103) -> #DIV/0!

Sheet Gastos
A2: DESCRIÇÃO DOS GASTOS | B2: Total | C2: % Total | D2: Mês 1 | E2: Mês 2 | F2: Mês 3 | G2: Mês 4 | H2: Mês 5 | I2: Mês 6 | J2: Mês 7 | K2: Mês 8 | L2: Mês 9 | M2: Mês 10 | N2: Mês 11 | O2: Mês 12 | P2: Mês 13 | Q2: Mês 14 | R2: Mês 15 | S2: Mês 16 | T2: Mês 17 | U2: Mês 18 | V2: Mês 19 | W2: Mês 20 | X2: Mês 21 | Y2: Mês 22 | Z2: Mês 23 | AA2: Mês 24 | AB2: Mês 25 | AC2: Mês 26 | AD2: Mês 27 | AE2: Mês 28 | AF2: Mês 29 | AG2: Mês 30 | AH2: Mês 31 | AI2: Mês 32 | AJ2: Mês 33 | AK2: Mês 34 | AL2: Mês 35 | AM2: Mês 36 | AN2: Mês 37 | AO2: Mês 38 | AP2: Mês 39 | AQ2: Mês 40 | AR2: Mês 41 | AS2: Mês 42 | AT2: Mês 43 | AU2: Mês 44 | AV2: Mês 45 | AW2: Mês 46 | AX2: Mês 47 | AY2: Mês 48 | AZ2: Mês 49 | BA2: Mês 50 | BB2: Mês 51 | BC2: Mês 52 | BD2: Mês 53 | BE2: Mês 54 | BF2: Mês 55 | BG2: Mês 56 | BH2: Mês 57 | BI2: Mês 58 | BJ2: Mês 59 | BK2: Mês 60
B3: =SUM(D3:BK3) -> 0 | C3: =B3/SUM($B$3:$B$103) -> #DIV/0!
B4: =SUM(D4:BK4) -> 0 | C4: =B4/SUM($B$3:$B$103) -> #DIV/0!
B5: =SUM(D5:BK5) -> 0 | C5: =B5/SUM($B$3:$B$103) -> #DIV/0!
B6: =SUM(D6:BK6) -> 0 | C6: =B6/SUM($B$3:$B$103) -> #DIV/0!
B7: =SUM(D7:BK7) -> 0 | C7: =B7/SUM($B$3:$B$103) -> #DIV/0!
B8: =SUM(D8:BK8) -> 0 | C8: =B8/SUM($B$3:$B$103) -> #DIV/0!
B9: =SUM(D9:BK9) -> 0 | C9: =B9/SUM($B$3:$B$103) -> #DIV/0!
B10: =SUM(D10:BK10) -> 0 | C10: =B10/SUM($B$3:$B$103) -> #DIV/0!
B11: =SUM(D11:BK11) -> 0 | C11: =B11/SUM($B$3:$B$103) -> #DIV/0!
B12: =SUM(D12:BK12) -> 0 | C12: =B12/SUM($B$3:$B$103) -> #DIV/0!
B13: =SUM(D13:BK13) -> 0 | C13: =B13/SUM($B$3:$B$103) -> #DIV/0!
B14: =SUM(D14:BK14) -> 0 | C14: =B14/SUM($B$3:$B$103) -> #DIV/0!
... B103: =SUM(D103:BK103) -> 0 | C103: =B103/SUM($B$3:$B$103) -> #DIV/0!

Sheet Depreciação
A2: DESCRIÇÃO DAS DEPRECIAÇÕES | B2: Total | C2: % Total | D2: Mês 1 | E2: Mês 2 | F2: Mês 3 | G2: Mês 4 | H2: Mês 5 | I2: Mês 6 | J2: Mês 7 | K2: Mês 8 | L2: Mês 9 | M2: Mês 10 | N2: Mês 11 | O2: Mês 12 | P2: Mês 13 | Q2: Mês 14 | R2: Mês 15 | S2: Mês 16 | T2: Mês 17 | U2: Mês 18 | V2: Mês 19 | W2: Mês 20 | X2: Mês 21 | Y2: Mês 22 | Z2: Mês 23 | AA2: Mês 24 | AB2: Mês 25 | AC2: Mês 26 | AD2: Mês 27 | AE2: Mês 28 | AF2: Mês 29 | AG2: Mês 30 | AH2: Mês 31 | AI2: Mês 32 | AJ2: Mês 33 | AK2: Mês 34 | AL2: Mês 35 | AM2: Mês 36 | AN2: Mês 37 | AO2: Mês 38 | AP2: Mês 39 | AQ2: Mês 40 | AR2: Mês 41 | AS2: Mês 42 | AT2: Mês 43 | AU2: Mês 44 | AV2: Mês 45 | AW2: Mês 46 | AX2: Mês 47 | AY2: Mês 48 | AZ2: Mês 49 | BA2: Mês 50 | BB2: Mês 51 | BC2: Mês 52 | BD2: Mês 53 | BE2: Mês 54 | BF2: Mês 55 | BG2: Mês 56 | BH2: Mês 57 | BI2: Mês 58 | BJ2: Mês 59 | BK2: Mês 60
B3: =SUM(D3:BK3) -> 0 | C3: =B3/SUM($B$3:$B$103) -> #DIV/0!
B4: =SUM(D4:BK4) -> 0 | C4: =B4/SUM($B$3:$B$103) -> #DIV/0!
B5: =SUM(D5:BK5) -> 0 | C5: =B5/SUM($B$3:$B$103) -> #DIV/0!
B6: =SUM(D6:BK6) -> 0 | C6: =B6/SUM($B$3:$B$103) -> #DIV/0!
B7: =SUM(D7:BK7) -> 0 | C7: =B7/SUM($B$3:$B$103) -> #DIV/0!
B8: =SUM(D8:BK8) -> 0 | C8: =B8/SUM($B$3:$B$103) -> #DIV/0!
B9: =SUM(D9:BK9) -> 0 | C9: =B9/SUM($B$3:$B$103) -> #DIV/0!
B10: =SUM(D10:BK10) -> 0 | C10: =B10/SUM($B$3:$B$103) -> #DIV/0!
B11: =SUM(D11:BK11) -> 0 | C11: =B11/SUM($B$3:$B$103) -> #DIV/0!
B12: =SUM(D12:BK12) -> 0 | C12: =B12/SUM($B$3:$B$103) -> #DIV/0!
B13: =SUM(D13:BK13) -> 0 | C13: =B13/SUM($B$3:$B$103) -> #DIV/0!
B14: =SUM(D14:BK14) -> 0 | C14: =B14/SUM($B$3:$B$103) -> #DIV/0!
... B103: =SUM(D103:BK103) -> 0 | C103: =B103/SUM($B$3:$B$103) -> #DIV/0!

Sheet Indicadores
A3: DRE - Demonstrativo de Resultado do Exercício
A4: FLUXO DE CAIXA | B4: INICIAL | C4: 1º Ano | D4: 2º Ano | E4: 3º Ano | F4: 4º Ano | G4: 5º Ano
A5: Receita Bruta | C5: =SUM(Receitas!D$3:O$103) -> 0 | D5: =SUM(Receitas!P$3:AA$103) -> 0 | E5: =SUM(Receitas!AB$3:AM$103) -> 0 | F5: =SUM(Receitas!AN$3:AY$103) -> 0 | G5: =SUM(Receitas!AZ$3:BK$103) -> 0
A6: PIS/COFINS/ISS | C6: =C5*Taxas!$B$6 -> 0 | D6: =D5*Taxas!$B$6 -> 0 | E6: =E5*Taxas!$B$6 -> 0 | F6: =F5*Taxas!$B$6 -> 0 | G6: =G5*Taxas!$B$6 -> 0
A7: Receita Líquida | C7: =C5-C6 -> 0 | D7: =D5-D6 -> 0 | E7: =E5-E6 -> 0 | F7: =F5-F6 -> 0 | G7: =G5-G6 -> 0
A8: Gastos | C8: =SUM(Gastos!D$3:O$103) -> 0 | D8: =SUM(Gastos!P$3:AA$103) -> 0 | E8: =SUM(Gastos!AB$3:AM$103) -> 0 | F8: =SUM(Gastos!AN$3:AY$103) -> 0 | G8: =SUM(Gastos!AZ$3:BK$103) -> 0 | J8: Em todas as abas da Planilha de Viabilidade Econômica, preencha apenas os campos com fundo verde claro. Todos as outras informações são geradas automaticamente.
A9: Investimentos | B9: =Investimentos!B3 -> 0 | C9: =SUM(Investimentos!D$4:O$103) -> 0 | D9: =SUM(Investimentos!P$4:AA$103) -> 0 | E9: =SUM(Investimentos!AB$4:AM$103) -> 0 | F9: =SUM(Investimentos!AN$4:AY$103) -> 0 | G9: =SUM(Investimentos!AZ$4:BK$103) -> 0
A10: EBITDA | C10: =C7-(SUM(C8,C9)) -> 0 | D10: =D7-(SUM(D8,D9)) -> 0 | E10: =E7-(SUM(E8,E9)) -> 0 | F10: =F7-(SUM(F8,F9)) -> 0 | G10: =G7-(SUM(G8,G9)) -> 0
A11: Depreciação | C11: =SUM(Depreciação!D$3:O$103) -> 0 | D11: =SUM(Depreciação!P$3:AA$103) -> 0 | E11: =SUM(Depreciação!AB$3:AM$103) -> 0 | F11: =SUM(Depreciação!AN$3:AY$103) -> 0 | G11: =SUM(Depreciação!AZ$3:BK$103) -> 0
A12: IR (Imposto de Renda) | C12: =IF(C10>=0,C10*Taxas!$B$7,0) -> 0 | D12: =IF(D10>=0,D10*Taxas!$B$7,0) -> 0 | E12: =IF(E10>=0,E10*Taxas!$B$7,0) -> 0 | F12: =IF(F10>=0,F10*Taxas!$B$7,0) -> 0 | G12: =IF(G10>=0,G10*Taxas!$B$7,0) -> 0
A13: Lucro Líquido | B13: =-B9 -> 0 | C13: =C10-(C11+C12) -> 0 | D13: =D10-(D11+D12) -> 0 | E13: =E10-(E11+E12) -> 0 | F13: =F10-(F11+F12) -> 0 | G13: =G10-(G11+G12) -> 0
A14: Lucro Livre Acumulado | B14: =B13 -> 0 | C14: =C13 -> 0 | D14: =C14+D13 -> 0 | E14: =D14+E13 -> 0 | F14: =E14+F13 -> 0 | G14: =F14+G13 -> 0
A17: INDICADORES
A18: VPL | B18: =NPV(Taxas!B9,Indicadores!B13:G13) -> 0 | E18: =IF(B18>0,1,0) -> 0
A19: TIR | B19: =IRR(B13:G13) -> #NUM! | E19: =IF(B19>Taxas!B8,1,0) -> #NUM!
A20: ROI | B20: =(SUM(B5:G5)/(SUM(B8:G9))) -> #DIV/0!
A22: =IF(SUM(E18:E19)=2,"O investimento está com indicação positiva, mostrando ser interessante, pois o VPL é maior que 0 (Zero) e o TIR é maior que o TMA","") -> #NUM!
